{
"meta":{"test_sets":[],"test_metrics":[],"learn_metrics":[{"best_value":"Min","name":"Logloss"}],"launch_mode":"Train","parameters":"","iteration_count":1000,"learn_sets":["learn"],"name":"experiment"},
"iterations":[
{"learn":[0.6888993181],"iteration":0,"passed_time":0.008460085911,"remaining_time":8.451625825},
{"learn":[0.6847339343],"iteration":1,"passed_time":0.01293595867,"remaining_time":6.455043378},
{"learn":[0.6811690268],"iteration":2,"passed_time":0.01834688375,"remaining_time":6.097281034},
{"learn":[0.6774592962],"iteration":3,"passed_time":0.02157690103,"remaining_time":5.372648357},
{"learn":[0.6738041466],"iteration":4,"passed_time":0.02416772522,"remaining_time":4.809377319},
{"learn":[0.6697113993],"iteration":5,"passed_time":0.02685304054,"remaining_time":4.448653716},
{"learn":[0.6655819752],"iteration":6,"passed_time":0.02973146846,"remaining_time":4.217621169},
{"learn":[0.6610919478],"iteration":7,"passed_time":0.03274558735,"remaining_time":4.060452832},
{"learn":[0.6569897935],"iteration":8,"passed_time":0.03521855865,"remaining_time":3.877954624},
{"learn":[0.6543432996],"iteration":9,"passed_time":0.03739370422,"remaining_time":3.701976718},
{"learn":[0.6512046547],"iteration":10,"passed_time":0.03943833276,"remaining_time":3.545864646},
{"learn":[0.6474876635],"iteration":11,"passed_time":0.0410498966,"remaining_time":3.37977482},
{"learn":[0.6437380177],"iteration":12,"passed_time":0.04291091656,"remaining_time":3.257928818},
{"learn":[0.6397087015],"iteration":13,"passed_time":0.04462014348,"remaining_time":3.142532962},
{"learn":[0.635788538],"iteration":14,"passed_time":0.04613627104,"remaining_time":3.029615132},
{"learn":[0.6330323202],"iteration":15,"passed_time":0.04723419407,"remaining_time":2.904902935},
{"learn":[0.6299322256],"iteration":16,"passed_time":0.04826911592,"remaining_time":2.791090644},
{"learn":[0.6261592391],"iteration":17,"passed_time":0.04933379123,"remaining_time":2.691432388},
{"learn":[0.6231260715],"iteration":18,"passed_time":0.05022773363,"remaining_time":2.593337194},
{"learn":[0.6199211404],"iteration":19,"passed_time":0.05115016016,"remaining_time":2.506357848},
{"learn":[0.6166696243],"iteration":20,"passed_time":0.05207269175,"remaining_time":2.427579296},
{"learn":[0.613725331],"iteration":21,"passed_time":0.05299391897,"remaining_time":2.35582058},
{"learn":[0.6109977881],"iteration":22,"passed_time":0.05389822629,"remaining_time":2.289502917},
{"learn":[0.6081309277],"iteration":23,"passed_time":0.0548505866,"remaining_time":2.230590522},
{"learn":[0.6053403452],"iteration":24,"passed_time":0.05574359758,"remaining_time":2.174000306},
{"learn":[0.602812311],"iteration":25,"passed_time":0.05675129567,"remaining_time":2.125990845},
{"learn":[0.6000140101],"iteration":26,"passed_time":0.05774933734,"remaining_time":2.081115008},
{"learn":[0.5974426408],"iteration":27,"passed_time":0.05862581651,"remaining_time":2.035153345},
{"learn":[0.5952620528],"iteration":28,"passed_time":0.05962692222,"remaining_time":1.996473844},
{"learn":[0.5934534248],"iteration":29,"passed_time":0.06047995965,"remaining_time":1.955518695},
{"learn":[0.5906878263],"iteration":30,"passed_time":0.06156987046,"remaining_time":1.924554983},
{"learn":[0.5883211767],"iteration":31,"passed_time":0.06252753107,"remaining_time":1.891457815},
{"learn":[0.5859067573],"iteration":32,"passed_time":0.06350817767,"remaining_time":1.860982055},
{"learn":[0.5839662009],"iteration":33,"passed_time":0.06455638932,"remaining_time":1.834160944},
{"learn":[0.5811442645],"iteration":34,"passed_time":0.06544525576,"remaining_time":1.804419195},
{"learn":[0.5785028857],"iteration":35,"passed_time":0.06663276906,"remaining_time":1.784277483},
{"learn":[0.5762328717],"iteration":36,"passed_time":0.06753197344,"remaining_time":1.757656498},
{"learn":[0.5745501265],"iteration":37,"passed_time":0.06853766859,"remaining_time":1.735085189},
{"learn":[0.5724262933],"iteration":38,"passed_time":0.06952302388,"remaining_time":1.713118614},
{"learn":[0.5707756958],"iteration":39,"passed_time":0.07039809646,"remaining_time":1.689554315},
{"learn":[0.568789171],"iteration":40,"passed_time":0.07138785992,"remaining_time":1.669779455},
{"learn":[0.5664545041],"iteration":41,"passed_time":0.07234059649,"remaining_time":1.650054558},
{"learn":[0.5640631391],"iteration":42,"passed_time":0.07334616953,"remaining_time":1.632378703},
{"learn":[0.5617060542],"iteration":43,"passed_time":0.07434323529,"remaining_time":1.615275749},
{"learn":[0.5599598803],"iteration":44,"passed_time":0.07540684808,"remaining_time":1.600300887},
{"learn":[0.5581988569],"iteration":45,"passed_time":0.07636260041,"remaining_time":1.58369393},
{"learn":[0.5559852453],"iteration":46,"passed_time":0.07746679493,"remaining_time":1.570762884},
{"learn":[0.5540554029],"iteration":47,"passed_time":0.07837901177,"remaining_time":1.554517067},
{"learn":[0.5522027907],"iteration":48,"passed_time":0.07932946853,"remaining_time":1.539639277},
{"learn":[0.5499872585],"iteration":49,"passed_time":0.08021726298,"remaining_time":1.524127997},
{"learn":[0.5474107617],"iteration":50,"passed_time":0.08124292739,"remaining_time":1.511755649},
{"learn":[0.5458247139],"iteration":51,"passed_time":0.08215554037,"remaining_time":1.497758698},
{"learn":[0.5439658677],"iteration":52,"passed_time":0.08306435336,"remaining_time":1.484187597},
{"learn":[0.5417491213],"iteration":53,"passed_time":0.0839471433,"remaining_time":1.470629584},
{"learn":[0.5397448956],"iteration":54,"passed_time":0.08488747557,"remaining_time":1.458521171},
{"learn":[0.5377272332],"iteration":55,"passed_time":0.08581443048,"remaining_time":1.446586114},
{"learn":[0.5359796767],"iteration":56,"passed_time":0.08691984512,"remaining_time":1.437989718},
{"learn":[0.5346718311],"iteration":57,"passed_time":0.08785303743,"remaining_time":1.426854504},
{"learn":[0.5331664151],"iteration":58,"passed_time":0.08880142973,"remaining_time":1.416307549},
{"learn":[0.5311905371],"iteration":59,"passed_time":0.08979060064,"remaining_time":1.40671941},
{"learn":[0.5293826003],"iteration":60,"passed_time":0.09083941573,"remaining_time":1.398331334},
{"learn":[0.5272869452],"iteration":61,"passed_time":0.09182144574,"remaining_time":1.389169615},
{"learn":[0.5251887772],"iteration":62,"passed_time":0.09300896093,"remaining_time":1.383323752},
{"learn":[0.5233925081],"iteration":63,"passed_time":0.0939669732,"remaining_time":1.374266983},
{"learn":[0.521468653],"iteration":64,"passed_time":0.0949693776,"remaining_time":1.36609797},
{"learn":[0.5195561602],"iteration":65,"passed_time":0.09590812059,"remaining_time":1.357245222},
{"learn":[0.5183712218],"iteration":66,"passed_time":0.09689270869,"remaining_time":1.349267123},
{"learn":[0.5171217586],"iteration":67,"passed_time":0.0978100228,"remaining_time":1.340572665},
{"learn":[0.5158228725],"iteration":68,"passed_time":0.09871804162,"remaining_time":1.331978214},
{"learn":[0.5144342181],"iteration":69,"passed_time":0.09971485795,"remaining_time":1.324783113},
{"learn":[0.5132649099],"iteration":70,"passed_time":0.1007120804,"remaining_time":1.317767925},
{"learn":[0.5114805761],"iteration":71,"passed_time":0.101832641,"remaining_time":1.312509596},
{"learn":[0.5100979898],"iteration":72,"passed_time":0.1029081432,"remaining_time":1.306792449},
{"learn":[0.5086626062],"iteration":73,"passed_time":0.1039429974,"remaining_time":1.300692102},
{"learn":[0.5071873392],"iteration":74,"passed_time":0.1049946763,"remaining_time":1.294934341},
{"learn":[0.50580699],"iteration":75,"passed_time":0.1059331022,"remaining_time":1.287923505},
{"learn":[0.5042225631],"iteration":76,"passed_time":0.1068783131,"remaining_time":1.281151727},
{"learn":[0.5031693289],"iteration":77,"passed_time":0.1078418017,"remaining_time":1.2747454},
{"learn":[0.5019090515],"iteration":78,"passed_time":0.1088670193,"remaining_time":1.269196517},
{"learn":[0.5006032384],"iteration":79,"passed_time":0.1099466253,"remaining_time":1.264386191},
{"learn":[0.4997514702],"iteration":80,"passed_time":0.1108935623,"remaining_time":1.258162762},
{"learn":[0.4983891861],"iteration":81,"passed_time":0.1118876345,"remaining_time":1.252595713},
{"learn":[0.4967853933],"iteration":82,"passed_time":0.1128812188,"remaining_time":1.247133466},
{"learn":[0.4951171292],"iteration":83,"passed_time":0.1138007744,"remaining_time":1.240970349},
{"learn":[0.4938660927],"iteration":84,"passed_time":0.1146719921,"remaining_time":1.234410267},
{"learn":[0.4923257186],"iteration":85,"passed_time":0.1156070146,"remaining_time":1.228660597},
{"learn":[0.4910822565],"iteration":86,"passed_time":0.1165534995,"remaining_time":1.223141897},
{"learn":[0.4898917747],"iteration":87,"passed_time":0.1175008762,"remaining_time":1.217736353},
{"learn":[0.4886831382],"iteration":88,"passed_time":0.1184235431,"remaining_time":1.212178065},
{"learn":[0.4870680218],"iteration":89,"passed_time":0.1193520849,"remaining_time":1.206782192},
{"learn":[0.4861030808],"iteration":90,"passed_time":0.1202576081,"remaining_time":1.201254569},
{"learn":[0.484933621],"iteration":91,"passed_time":0.1212695255,"remaining_time":1.196877491},
{"learn":[0.4837430564],"iteration":92,"passed_time":0.1222724903,"remaining_time":1.19248547},
{"learn":[0.4824189607],"iteration":93,"passed_time":0.1231473542,"remaining_time":1.186930882},
{"learn":[0.4813753275],"iteration":94,"passed_time":0.1240529128,"remaining_time":1.181767222},
{"learn":[0.4800614207],"iteration":95,"passed_time":0.1249811584,"remaining_time":1.176905908},
{"learn":[0.4793368537],"iteration":96,"passed_time":0.125874389,"remaining_time":1.171799724},
{"learn":[0.4780266956],"iteration":97,"passed_time":0.1267517068,"remaining_time":1.166633057},
{"learn":[0.4772001573],"iteration":98,"passed_time":0.1276288041,"remaining_time":1.161551035},
{"learn":[0.4761158325],"iteration":99,"passed_time":0.1285401226,"remaining_time":1.156861104},
{"learn":[0.4754855513],"iteration":100,"passed_time":0.1294669554,"remaining_time":1.152384089},
{"learn":[0.4746072769],"iteration":101,"passed_time":0.1303749425,"remaining_time":1.147810769},
{"learn":[0.4735783684],"iteration":102,"passed_time":0.1313957071,"remaining_time":1.144290769},
{"learn":[0.4723746449],"iteration":103,"passed_time":0.1325240069,"remaining_time":1.14174529},
{"learn":[0.4711758665],"iteration":104,"passed_time":0.1334644887,"remaining_time":1.13762588},
{"learn":[0.4705153638],"iteration":105,"passed_time":0.1344669551,"remaining_time":1.134089225},
{"learn":[0.469243691],"iteration":106,"passed_time":0.1354047861,"remaining_time":1.130060504},
{"learn":[0.4680180646],"iteration":107,"passed_time":0.1364093837,"remaining_time":1.126640465},
{"learn":[0.4671616731],"iteration":108,"passed_time":0.1374641512,"remaining_time":1.123674851},
{"learn":[0.465902661],"iteration":109,"passed_time":0.1384156081,"remaining_time":1.119908102},
{"learn":[0.4649315239],"iteration":110,"passed_time":0.1394498048,"remaining_time":1.116854743},
{"learn":[0.4644481875],"iteration":111,"passed_time":0.1403563834,"remaining_time":1.112825612},
{"learn":[0.4634348942],"iteration":112,"passed_time":0.1413699739,"remaining_time":1.109691742},
{"learn":[0.4625863996],"iteration":113,"passed_time":0.1423683218,"remaining_time":1.106476606},
{"learn":[0.4613304422],"iteration":114,"passed_time":0.1433284615,"remaining_time":1.103005986},
{"learn":[0.4604029613],"iteration":115,"passed_time":0.1442967251,"remaining_time":1.09964056},
{"learn":[0.4594544294],"iteration":116,"passed_time":0.1452076693,"remaining_time":1.095883521},
{"learn":[0.458667341],"iteration":117,"passed_time":0.1462705262,"remaining_time":1.093310204},
{"learn":[0.4580400812],"iteration":118,"passed_time":0.147225288,"remaining_time":1.089962006},
{"learn":[0.4571327965],"iteration":119,"passed_time":0.148144207,"remaining_time":1.086390851},
{"learn":[0.4563559499],"iteration":120,"passed_time":0.1491526841,"remaining_time":1.083514127},
{"learn":[0.4557614312],"iteration":121,"passed_time":0.1501275684,"remaining_time":1.080426271},
{"learn":[0.454960125],"iteration":122,"passed_time":0.1510164841,"remaining_time":1.076759809},
{"learn":[0.4542681789],"iteration":123,"passed_time":0.1519123845,"remaining_time":1.07318749},
{"learn":[0.4534123944],"iteration":124,"passed_time":0.1528763677,"remaining_time":1.070134574},
{"learn":[0.452659505],"iteration":125,"passed_time":0.1539056409,"remaining_time":1.0675677},
{"learn":[0.4520023635],"iteration":126,"passed_time":0.1548982668,"remaining_time":1.064773125},
{"learn":[0.451424947],"iteration":127,"passed_time":0.1559050505,"remaining_time":1.062103156},
{"learn":[0.4505877616],"iteration":128,"passed_time":0.1569001161,"remaining_time":1.059379854},
{"learn":[0.4498519691],"iteration":129,"passed_time":0.1578966367,"remaining_time":1.056692876},
{"learn":[0.4488979945],"iteration":130,"passed_time":0.1588591556,"remaining_time":1.053806154},
{"learn":[0.4479670725],"iteration":131,"passed_time":0.1597936092,"remaining_time":1.050764036},
{"learn":[0.4471830421],"iteration":132,"passed_time":0.1607100553,"remaining_time":1.047636225},
{"learn":[0.4463923622],"iteration":133,"passed_time":0.1616426077,"remaining_time":1.04464551},
{"learn":[0.445345509],"iteration":134,"passed_time":0.1625823919,"remaining_time":1.041731622},
{"learn":[0.4444023451],"iteration":135,"passed_time":0.1635996172,"remaining_time":1.039338745},
{"learn":[0.4435944423],"iteration":136,"passed_time":0.1645866209,"remaining_time":1.036775576},
{"learn":[0.4428129813],"iteration":137,"passed_time":0.1654951069,"remaining_time":1.033744798},
{"learn":[0.4419462137],"iteration":138,"passed_time":0.1664018407,"remaining_time":1.030733704},
{"learn":[0.4411905523],"iteration":139,"passed_time":0.1672952886,"remaining_time":1.027671058},
{"learn":[0.440364863],"iteration":140,"passed_time":0.168317976,"remaining_time":1.025426535},
{"learn":[0.4393251695],"iteration":141,"passed_time":0.1692493339,"remaining_time":1.022647384},
{"learn":[0.4386999526],"iteration":142,"passed_time":0.1701300622,"remaining_time":1.019590653},
{"learn":[0.4379332268],"iteration":143,"passed_time":0.171096019,"remaining_time":1.01707078},
{"learn":[0.437473784],"iteration":144,"passed_time":0.1720108029,"remaining_time":1.014270597},
{"learn":[0.4368234121],"iteration":145,"passed_time":0.1730392948,"remaining_time":1.012161354},
{"learn":[0.4359715942],"iteration":146,"passed_time":0.1739909286,"remaining_time":1.00962083},
{"learn":[0.4352468391],"iteration":147,"passed_time":0.1749029249,"remaining_time":1.006873595},
{"learn":[0.4346566646],"iteration":148,"passed_time":0.175900994,"remaining_time":1.00464259},
{"learn":[0.4338960348],"iteration":149,"passed_time":0.1769710889,"remaining_time":1.00283617},
{"learn":[0.4333755355],"iteration":150,"passed_time":0.1780583943,"remaining_time":1.00113627},
{"learn":[0.4328467399],"iteration":151,"passed_time":0.1791012753,"remaining_time":0.9991965886},
{"learn":[0.4321115302],"iteration":152,"passed_time":0.1800628959,"remaining_time":0.9968187766},
{"learn":[0.4315284586],"iteration":153,"passed_time":0.1810282625,"remaining_time":0.9944799357},
{"learn":[0.4308541751],"iteration":154,"passed_time":0.1819774878,"remaining_time":0.9920708206},
{"learn":[0.430322492],"iteration":155,"passed_time":0.1830060762,"remaining_time":0.9901097967},
{"learn":[0.4293661853],"iteration":156,"passed_time":0.1839147916,"remaining_time":0.9875170023},
{"learn":[0.4286666194],"iteration":157,"passed_time":0.1848336155,"remaining_time":0.9849993942},
{"learn":[0.4280779561],"iteration":158,"passed_time":0.1857124081,"remaining_time":0.9822901587},
{"learn":[0.4274572241],"iteration":159,"passed_time":0.1866109963,"remaining_time":0.9797077305},
{"learn":[0.4269866452],"iteration":160,"passed_time":0.1875324133,"remaining_time":0.9772651848},
{"learn":[0.4262521165],"iteration":161,"passed_time":0.188440496,"remaining_time":0.9747724423},
{"learn":[0.4256355472],"iteration":162,"passed_time":0.1893330711,"remaining_time":0.9722195123},
{"learn":[0.4249268671],"iteration":163,"passed_time":0.1903672939,"remaining_time":0.9704088884},
{"learn":[0.4246359668],"iteration":164,"passed_time":0.1913019591,"remaining_time":0.9681038534},
{"learn":[0.42396696],"iteration":165,"passed_time":0.1922562684,"remaining_time":0.9659140229},
{"learn":[0.4231187462],"iteration":166,"passed_time":0.1932689501,"remaining_time":0.9640301524},
{"learn":[0.4223214434],"iteration":167,"passed_time":0.1942125078,"remaining_time":0.9618143244},
{"learn":[0.4218980017],"iteration":168,"passed_time":0.1951107363,"remaining_time":0.9593906618},
{"learn":[0.4212903423],"iteration":169,"passed_time":0.1960404547,"remaining_time":0.9571386906},
{"learn":[0.4207506439],"iteration":170,"passed_time":0.1971117683,"remaining_time":0.955588631},
{"learn":[0.4202952178],"iteration":171,"passed_time":0.1980531872,"remaining_time":0.9534188315},
{"learn":[0.4198401149],"iteration":172,"passed_time":0.1990170616,"remaining_time":0.9513705776},
{"learn":[0.4193802983],"iteration":173,"passed_time":0.2000354369,"remaining_time":0.949593511},
{"learn":[0.4188941843],"iteration":174,"passed_time":0.201101207,"remaining_time":0.9480485471},
{"learn":[0.4184863288],"iteration":175,"passed_time":0.2020847926,"remaining_time":0.9461242565},
{"learn":[0.4177910841],"iteration":176,"passed_time":0.2031294391,"remaining_time":0.9444945104},
{"learn":[0.4174209695],"iteration":177,"passed_time":0.2041621123,"remaining_time":0.9428160468},
{"learn":[0.4171820935],"iteration":178,"passed_time":0.2051250434,"remaining_time":0.9408249199},
{"learn":[0.4164472262],"iteration":179,"passed_time":0.2061436086,"remaining_time":0.9390986613},
{"learn":[0.4158091849],"iteration":180,"passed_time":0.2071078237,"remaining_time":0.9371342962},
{"learn":[0.4153466112],"iteration":181,"passed_time":0.2081455838,"remaining_time":0.9355114702},
{"learn":[0.4146929512],"iteration":182,"passed_time":0.2091763152,"remaining_time":0.9338636587},
{"learn":[0.4143722841],"iteration":183,"passed_time":0.2101612555,"remaining_time":0.9320194807},
{"learn":[0.4137349301],"iteration":184,"passed_time":0.2110831036,"remaining_time":0.9299066457},
{"learn":[0.413306954],"iteration":185,"passed_time":0.2119980518,"remaining_time":0.9277764202},
{"learn":[0.4125317273],"iteration":186,"passed_time":0.2130975012,"remaining_time":0.9264613286},
{"learn":[0.4118644073],"iteration":187,"passed_time":0.2141175785,"remaining_time":0.9248057112},
{"learn":[0.4109112945],"iteration":188,"passed_time":0.2150714656,"remaining_time":0.9228727968},
{"learn":[0.4103388974],"iteration":189,"passed_time":0.2160704884,"remaining_time":0.9211426083},
{"learn":[0.410011816],"iteration":190,"passed_time":0.2171568794,"remaining_time":0.919790133},
{"learn":[0.409380114],"iteration":191,"passed_time":0.2182246447,"remaining_time":0.9183620466},
{"learn":[0.4086967374],"iteration":192,"passed_time":0.2192212926,"remaining_time":0.9166403271},
{"learn":[0.4082219648],"iteration":193,"passed_time":0.22022228,"remaining_time":0.9149441117},
{"learn":[0.407516269],"iteration":194,"passed_time":0.2212296529,"remaining_time":0.9132813877},
{"learn":[0.4071825847],"iteration":195,"passed_time":0.2223542176,"remaining_time":0.9121060762},
{"learn":[0.4064849802],"iteration":196,"passed_time":0.2234196208,"remaining_time":0.9106901294},
{"learn":[0.4061650006],"iteration":197,"passed_time":0.2244309135,"remaining_time":0.9090585485},
{"learn":[0.4055643076],"iteration":198,"passed_time":0.2255905802,"remaining_time":0.9080304257},
{"learn":[0.4048930412],"iteration":199,"passed_time":0.2266154168,"remaining_time":0.9064616672},
{"learn":[0.4042968512],"iteration":200,"passed_time":0.2276384076,"remaining_time":0.9048909836},
{"learn":[0.4039001143],"iteration":201,"passed_time":0.2286356921,"remaining_time":0.9032241696},
{"learn":[0.4035745639],"iteration":202,"passed_time":0.2296559615,"remaining_time":0.9016541937},
{"learn":[0.4030309668],"iteration":203,"passed_time":0.2305941384,"remaining_time":0.8997692853},
{"learn":[0.4027160152],"iteration":204,"passed_time":0.2314977065,"remaining_time":0.8977593984},
{"learn":[0.4019715992],"iteration":205,"passed_time":0.2324507124,"remaining_time":0.895950804},
{"learn":[0.401572983],"iteration":206,"passed_time":0.2333226968,"remaining_time":0.8938400895},
{"learn":[0.4012438462],"iteration":207,"passed_time":0.2343442081,"remaining_time":0.8923106386},
{"learn":[0.4007957883],"iteration":208,"passed_time":0.2353020803,"remaining_time":0.8905451938},
{"learn":[0.4004448834],"iteration":209,"passed_time":0.2364851206,"remaining_time":0.8896345013},
{"learn":[0.4000219644],"iteration":210,"passed_time":0.2375644791,"remaining_time":0.888333526},
{"learn":[0.399611754],"iteration":211,"passed_time":0.2386086943,"remaining_time":0.8869040147},
{"learn":[0.3991841073],"iteration":212,"passed_time":0.2396147359,"remaining_time":0.8853370758},
{"learn":[0.3984528472],"iteration":213,"passed_time":0.2406631648,"remaining_time":0.8839310632},
{"learn":[0.3980332502],"iteration":214,"passed_time":0.2417097398,"remaining_time":0.8825216082},
{"learn":[0.3976453244],"iteration":215,"passed_time":0.2427200533,"remaining_time":0.8809838971},
{"learn":[0.3971916653],"iteration":216,"passed_time":0.2436685317,"remaining_time":0.8792279278},
{"learn":[0.3968989091],"iteration":217,"passed_time":0.2447043074,"remaining_time":0.8777925154},
{"learn":[0.3965770194],"iteration":218,"passed_time":0.2457574402,"remaining_time":0.8764226521},
{"learn":[0.3960956614],"iteration":219,"passed_time":0.2467003046,"remaining_time":0.8746647162},
{"learn":[0.3957059021],"iteration":220,"passed_time":0.2476456555,"remaining_time":0.8729229216},
{"learn":[0.3954436997],"iteration":221,"passed_time":0.2486306436,"remaining_time":0.8713272103},
{"learn":[0.3951159463],"iteration":222,"passed_time":0.2496922477,"remaining_time":0.8700039305},
{"learn":[0.3947817812],"iteration":223,"passed_time":0.2507211134,"remaining_time":0.8685695716},
{"learn":[0.3943782531],"iteration":224,"passed_time":0.2516250298,"remaining_time":0.8667084361},
{"learn":[0.3938834857],"iteration":225,"passed_time":0.2526418817,"remaining_time":0.8652425506},
{"learn":[0.3931799639],"iteration":226,"passed_time":0.2536050916,"remaining_time":0.863597955},
{"learn":[0.3928642908],"iteration":227,"passed_time":0.254527635,"remaining_time":0.8618216413},
{"learn":[0.3923603265],"iteration":228,"passed_time":0.2554101807,"remaining_time":0.8599181194},
{"learn":[0.3918734132],"iteration":229,"passed_time":0.2564767799,"remaining_time":0.8586396546},
{"learn":[0.3914222396],"iteration":230,"passed_time":0.2575044937,"remaining_time":0.8572335741},
{"learn":[0.3908981829],"iteration":231,"passed_time":0.2585256278,"remaining_time":0.8558089748},
{"learn":[0.3903056806],"iteration":232,"passed_time":0.2595590086,"remaining_time":0.8544281529},
{"learn":[0.3897873192],"iteration":233,"passed_time":0.2605203893,"remaining_time":0.8528146076},
{"learn":[0.3894327579],"iteration":234,"passed_time":0.2613972092,"remaining_time":0.8509313406},
{"learn":[0.3890170293],"iteration":235,"passed_time":0.2622988836,"remaining_time":0.849137064},
{"learn":[0.3883834875],"iteration":236,"passed_time":0.2631643069,"remaining_time":0.8472336125},
{"learn":[0.3880074377],"iteration":237,"passed_time":0.2642110807,"remaining_time":0.8459195106},
{"learn":[0.3877128655],"iteration":238,"passed_time":0.2651865075,"remaining_time":0.8443804694},
{"learn":[0.3873960877],"iteration":239,"passed_time":0.2662187335,"remaining_time":0.8430259894},
{"learn":[0.3871157536],"iteration":240,"passed_time":0.2671520697,"remaining_time":0.8413627423},
{"learn":[0.3868126248],"iteration":241,"passed_time":0.2680378413,"remaining_time":0.8395565443},
{"learn":[0.3863323182],"iteration":242,"passed_time":0.26893999,"remaining_time":0.83780894},
{"learn":[0.3860370938],"iteration":243,"passed_time":0.2700407825,"remaining_time":0.8366837361},
{"learn":[0.3855774805],"iteration":244,"passed_time":0.2709860195,"remaining_time":0.8350793661},
{"learn":[0.3851550824],"iteration":245,"passed_time":0.2719294267,"remaining_time":0.8334747468},
{"learn":[0.3847495782],"iteration":246,"passed_time":0.2728348282,"remaining_time":0.831759618},
{"learn":[0.3841718239],"iteration":247,"passed_time":0.2737064506,"remaining_time":0.829948592},
{"learn":[0.3835521723],"iteration":248,"passed_time":0.2746271865,"remaining_time":0.8282932412},
{"learn":[0.3833010647],"iteration":249,"passed_time":0.2755439715,"remaining_time":0.8266319144},
{"learn":[0.3828589334],"iteration":250,"passed_time":0.276463697,"remaining_time":0.824985295},
{"learn":[0.3822623833],"iteration":251,"passed_time":0.2773636004,"remaining_time":0.8232856075},
{"learn":[0.3820140746],"iteration":252,"passed_time":0.2782397833,"remaining_time":0.821522206},
{"learn":[0.3814206693],"iteration":253,"passed_time":0.2791096985,"remaining_time":0.8197473822},
{"learn":[0.3808270269],"iteration":254,"passed_time":0.2800147645,"remaining_time":0.8180823512},
{"learn":[0.3804425819],"iteration":255,"passed_time":0.281058072,"remaining_time":0.8168250217},
{"learn":[0.3801181561],"iteration":256,"passed_time":0.2821090325,"remaining_time":0.815591483},
{"learn":[0.3798194049],"iteration":257,"passed_time":0.2831555696,"remaining_time":0.8143466383},
{"learn":[0.3793640311],"iteration":258,"passed_time":0.2841366526,"remaining_time":0.8129160602},
{"learn":[0.3789450699],"iteration":259,"passed_time":0.2852344786,"remaining_time":0.8118212084},
{"learn":[0.3783303553],"iteration":260,"passed_time":0.2861140569,"remaining_time":0.8101083832},
{"learn":[0.3780025308],"iteration":261,"passed_time":0.287043586,"remaining_time":0.80854262},
{"learn":[0.3775493263],"iteration":262,"passed_time":0.2879951611,"remaining_time":0.8070434742},
{"learn":[0.3770506247],"iteration":263,"passed_time":0.288874241,"remaining_time":0.8053463687},
{"learn":[0.3768224156],"iteration":264,"passed_time":0.2897546455,"remaining_time":0.8036591112},
{"learn":[0.3765741391],"iteration":265,"passed_time":0.2907538903,"remaining_time":0.8023058477},
{"learn":[0.3761762064],"iteration":266,"passed_time":0.2916747389,"remaining_time":0.8007400135},
{"learn":[0.3758836101],"iteration":267,"passed_time":0.2925945183,"remaining_time":0.7991760725},
{"learn":[0.3756236797],"iteration":268,"passed_time":0.2935416077,"remaining_time":0.7976911347},
{"learn":[0.3751909287],"iteration":269,"passed_time":0.2944367361,"remaining_time":0.796069694},
{"learn":[0.3749926044],"iteration":270,"passed_time":0.295435093,"remaining_time":0.7947313019},
{"learn":[0.3746316212],"iteration":271,"passed_time":0.2963746198,"remaining_time":0.7932379529},
{"learn":[0.3744054616],"iteration":272,"passed_time":0.2972619589,"remaining_time":0.7916096855},
{"learn":[0.3739007245],"iteration":273,"passed_time":0.2981468166,"remaining_time":0.7899802514},
{"learn":[0.373503046],"iteration":274,"passed_time":0.2991152535,"remaining_time":0.7885765773},
{"learn":[0.373241639],"iteration":275,"passed_time":0.3001191662,"remaining_time":0.7872691172},
{"learn":[0.3730042686],"iteration":276,"passed_time":0.301254668,"remaining_time":0.7863073103},
{"learn":[0.3727633841],"iteration":277,"passed_time":0.3022183578,"remaining_time":0.7848980371},
{"learn":[0.3723738556],"iteration":278,"passed_time":0.3032533321,"remaining_time":0.7836761737},
{"learn":[0.3720903291],"iteration":279,"passed_time":0.3042558402,"remaining_time":0.7823721605},
{"learn":[0.3716105178],"iteration":280,"passed_time":0.3051257133,"remaining_time":0.7807309176},
{"learn":[0.3709923327],"iteration":281,"passed_time":0.306003529,"remaining_time":0.7791153682},
{"learn":[0.3707830968],"iteration":282,"passed_time":0.3069005643,"remaining_time":0.7775537266},
{"learn":[0.3705225953],"iteration":283,"passed_time":0.3077800578,"remaining_time":0.7759525402},
{"learn":[0.3702049612],"iteration":284,"passed_time":0.3086793768,"remaining_time":0.7744061557},
{"learn":[0.3699411166],"iteration":285,"passed_time":0.3095798216,"remaining_time":0.7728671071},
{"learn":[0.3695895728],"iteration":286,"passed_time":0.3104805329,"remaining_time":0.7713331706},
{"learn":[0.3693389244],"iteration":287,"passed_time":0.3113901301,"remaining_time":0.7698255995},
{"learn":[0.3691335336],"iteration":288,"passed_time":0.3122744171,"remaining_time":0.7682598981},
{"learn":[0.3688118306],"iteration":289,"passed_time":0.3132260897,"remaining_time":0.7668638748},
{"learn":[0.3686255893],"iteration":290,"passed_time":0.3141272397,"remaining_time":0.7653478109},
{"learn":[0.3682468122],"iteration":291,"passed_time":0.3150366183,"remaining_time":0.7638559101},
{"learn":[0.3680314773],"iteration":292,"passed_time":0.3159286884,"remaining_time":0.7623262208},
{"learn":[0.3677943277],"iteration":293,"passed_time":0.3168107793,"remaining_time":0.7607769054},
{"learn":[0.3674254335],"iteration":294,"passed_time":0.3176919146,"remaining_time":0.7592298299},
{"learn":[0.3669913371],"iteration":295,"passed_time":0.3186399103,"remaining_time":0.7578462732},
{"learn":[0.3668112658],"iteration":296,"passed_time":0.3195608929,"remaining_time":0.7564017094},
{"learn":[0.3665090258],"iteration":297,"passed_time":0.3205230989,"remaining_time":0.7550577699},
{"learn":[0.3662363467],"iteration":298,"passed_time":0.3214603004,"remaining_time":0.7536577611},
{"learn":[0.3658845467],"iteration":299,"passed_time":0.3224016062,"remaining_time":0.7522704145},
{"learn":[0.3654693104],"iteration":300,"passed_time":0.3233196899,"remaining_time":0.7508321038},
{"learn":[0.3651975093],"iteration":301,"passed_time":0.3242592777,"remaining_time":0.7494469398},
{"learn":[0.3646347167],"iteration":302,"passed_time":0.325189228,"remaining_time":0.7480425476},
{"learn":[0.364346245],"iteration":303,"passed_time":0.3263564729,"remaining_time":0.7471845564},
{"learn":[0.3641069123],"iteration":304,"passed_time":0.3274295656,"remaining_time":0.7461099937},
{"learn":[0.3635624525],"iteration":305,"passed_time":0.3286637972,"remaining_time":0.7454008996},
{"learn":[0.3630134516],"iteration":306,"passed_time":0.3296679906,"remaining_time":0.7441691124},
{"learn":[0.3626017381],"iteration":307,"passed_time":0.3305878439,"remaining_time":0.7427493116},
{"learn":[0.3622143902],"iteration":308,"passed_time":0.3314818867,"remaining_time":0.7412750281},
{"learn":[0.3618842531],"iteration":309,"passed_time":0.3324129904,"remaining_time":0.7398869786},
{"learn":[0.3614500581],"iteration":310,"passed_time":0.3333383063,"remaining_time":0.7384890451},
{"learn":[0.3610882313],"iteration":311,"passed_time":0.3343068184,"remaining_time":0.7371893943},
{"learn":[0.3608393468],"iteration":312,"passed_time":0.3353429916,"remaining_time":0.7360403681},
{"learn":[0.3606056331],"iteration":313,"passed_time":0.336308795,"remaining_time":0.7347383229},
{"learn":[0.3601602323],"iteration":314,"passed_time":0.3372181812,"remaining_time":0.7333157273},
{"learn":[0.3597579059],"iteration":315,"passed_time":0.338117944,"remaining_time":0.7318755497},
{"learn":[0.3594540376],"iteration":316,"passed_time":0.3391323107,"remaining_time":0.730685704},
{"learn":[0.3589087748],"iteration":317,"passed_time":0.3400506617,"remaining_time":0.7292910418},
{"learn":[0.3585787126],"iteration":318,"passed_time":0.3411881186,"remaining_time":0.7283671122},
{"learn":[0.3583253146],"iteration":319,"passed_time":0.3422909941,"remaining_time":0.7273683625},
{"learn":[0.3580148836],"iteration":320,"passed_time":0.3434025473,"remaining_time":0.7263873196},
{"learn":[0.3576620996],"iteration":321,"passed_time":0.3444242134,"remaining_time":0.7252162008},
{"learn":[0.3572702676],"iteration":322,"passed_time":0.3453924225,"remaining_time":0.723933963},
{"learn":[0.3569476761],"iteration":323,"passed_time":0.3464494382,"remaining_time":0.7228389513},
{"learn":[0.3566838184],"iteration":324,"passed_time":0.3473473515,"remaining_time":0.72141373},
{"learn":[0.3562972297],"iteration":325,"passed_time":0.3483479877,"remaining_time":0.7202041218},
{"learn":[0.355941496],"iteration":326,"passed_time":0.3492725393,"remaining_time":0.7188392016},
{"learn":[0.3554981614],"iteration":327,"passed_time":0.3503134737,"remaining_time":0.7177154095},
{"learn":[0.3552124999],"iteration":328,"passed_time":0.3512926242,"remaining_time":0.7164661121},
{"learn":[0.3547602752],"iteration":329,"passed_time":0.3522293288,"remaining_time":0.7151322736},
{"learn":[0.3544155919],"iteration":330,"passed_time":0.3531362718,"remaining_time":0.7137406823},
{"learn":[0.3542225626],"iteration":331,"passed_time":0.3540869482,"remaining_time":0.7124400042},
{"learn":[0.3536997204],"iteration":332,"passed_time":0.3550161716,"remaining_time":0.7110984577},
{"learn":[0.3534631064],"iteration":333,"passed_time":0.356012366,"remaining_time":0.7098929214},
{"learn":[0.3533647227],"iteration":334,"passed_time":0.3571241936,"remaining_time":0.7089181754},
{"learn":[0.3531252479],"iteration":335,"passed_time":0.3581213929,"remaining_time":0.7077160859},
{"learn":[0.3528015695],"iteration":336,"passed_time":0.3592527548,"remaining_time":0.7067791586},
{"learn":[0.3524134808],"iteration":337,"passed_time":0.3601627013,"remaining_time":0.7054074209},
{"learn":[0.3521625558],"iteration":338,"passed_time":0.3612450793,"remaining_time":0.7043746237},
{"learn":[0.35197964],"iteration":339,"passed_time":0.362209019,"remaining_time":0.7031116251},
{"learn":[0.3516840127],"iteration":340,"passed_time":0.3631209419,"remaining_time":0.7017498555},
{"learn":[0.3513305179],"iteration":341,"passed_time":0.3641068581,"remaining_time":0.7005330778},
{"learn":[0.3511522152],"iteration":342,"passed_time":0.3650110556,"remaining_time":0.6991611182},
{"learn":[0.3509083821],"iteration":343,"passed_time":0.3658995297,"remaining_time":0.6977618938},
{"learn":[0.350707324],"iteration":344,"passed_time":0.3668829308,"remaining_time":0.6965458541},
{"learn":[0.3504591356],"iteration":345,"passed_time":0.3679103331,"remaining_time":0.695414329},
{"learn":[0.3498663172],"iteration":346,"passed_time":0.3689574761,"remaining_time":0.694320553},
{"learn":[0.3496784651],"iteration":347,"passed_time":0.3699711252,"remaining_time":0.6931642921},
{"learn":[0.349414615],"iteration":348,"passed_time":0.3709639324,"remaining_time":0.6919699713},
{"learn":[0.3491052752],"iteration":349,"passed_time":0.3719523011,"remaining_time":0.6907685592},
{"learn":[0.3487354747],"iteration":350,"passed_time":0.3729137688,"remaining_time":0.6895186209},
{"learn":[0.348494134],"iteration":351,"passed_time":0.373767847,"remaining_time":0.6880726274},
{"learn":[0.3482340186],"iteration":352,"passed_time":0.3746750243,"remaining_time":0.6867273108},
{"learn":[0.3477694674],"iteration":353,"passed_time":0.375584967,"remaining_time":0.6853895161},
{"learn":[0.3475064145],"iteration":354,"passed_time":0.3765502068,"remaining_time":0.6841546011},
{"learn":[0.3473004724],"iteration":355,"passed_time":0.3774426011,"remaining_time":0.6827894244},
{"learn":[0.3469864965],"iteration":356,"passed_time":0.3783748558,"remaining_time":0.6814986899},
{"learn":[0.3466302865],"iteration":357,"passed_time":0.3792978034,"remaining_time":0.6801932676},
{"learn":[0.3463247371],"iteration":358,"passed_time":0.3802150101,"remaining_time":0.6788797256},
{"learn":[0.3460101956],"iteration":359,"passed_time":0.3810968005,"remaining_time":0.6775054231},
{"learn":[0.3457476333],"iteration":360,"passed_time":0.3820620899,"remaining_time":0.6762816495},
{"learn":[0.3454243243],"iteration":361,"passed_time":0.3829833602,"remaining_time":0.6749817233},
{"learn":[0.3450099609],"iteration":362,"passed_time":0.3839008116,"remaining_time":0.6736771818},
{"learn":[0.344698942],"iteration":363,"passed_time":0.3849852404,"remaining_time":0.6726665189},
{"learn":[0.3441289517],"iteration":364,"passed_time":0.3860377447,"remaining_time":0.671599912},
{"learn":[0.3438119075],"iteration":365,"passed_time":0.3871349957,"remaining_time":0.6706108941},
{"learn":[0.3434819565],"iteration":366,"passed_time":0.3882557319,"remaining_time":0.6696617938},
{"learn":[0.3432505339],"iteration":367,"passed_time":0.3892300985,"remaining_time":0.6684603866},
{"learn":[0.3429145776],"iteration":368,"passed_time":0.390188186,"remaining_time":0.6672323723},
{"learn":[0.3426861997],"iteration":369,"passed_time":0.3911292263,"remaining_time":0.6659767908},
{"learn":[0.3424645942],"iteration":370,"passed_time":0.3920661193,"remaining_time":0.6647158734},
{"learn":[0.3420567595],"iteration":371,"passed_time":0.3929441409,"remaining_time":0.6633573131},
{"learn":[0.3418065298],"iteration":372,"passed_time":0.3939630804,"remaining_time":0.6622382075},
{"learn":[0.3415830197],"iteration":373,"passed_time":0.3948966376,"remaining_time":0.660976725},
{"learn":[0.3412688438],"iteration":374,"passed_time":0.3957754491,"remaining_time":0.6596257485},
{"learn":[0.3411413485],"iteration":375,"passed_time":0.3966571851,"remaining_time":0.6582821369},
{"learn":[0.3408726755],"iteration":376,"passed_time":0.3975501274,"remaining_time":0.6569594944},
{"learn":[0.3406592793],"iteration":377,"passed_time":0.3984990877,"remaining_time":0.655731303},
{"learn":[0.3403246802],"iteration":378,"passed_time":0.3994401762,"remaining_time":0.6544916872},
{"learn":[0.3401122005],"iteration":379,"passed_time":0.4003651396,"remaining_time":0.653227333},
{"learn":[0.3398811731],"iteration":380,"passed_time":0.4012631087,"remaining_time":0.6519209036},
{"learn":[0.3395673009],"iteration":381,"passed_time":0.4022419653,"remaining_time":0.6507474727},
{"learn":[0.3394621999],"iteration":382,"passed_time":0.4031459352,"remaining_time":0.6494544178},
{"learn":[0.3393113728],"iteration":383,"passed_time":0.4041457583,"remaining_time":0.6483171539},
{"learn":[0.3391031807],"iteration":384,"passed_time":0.4051449548,"remaining_time":0.6471796031},
{"learn":[0.3388803604],"iteration":385,"passed_time":0.4060993033,"remaining_time":0.6459714307},
{"learn":[0.3386460899],"iteration":386,"passed_time":0.4070028279,"remaining_time":0.6446840658},
{"learn":[0.3384620961],"iteration":387,"passed_time":0.4079880819,"remaining_time":0.6435275931},
{"learn":[0.3382858288],"iteration":388,"passed_time":0.4091261455,"remaining_time":0.6426120178},
{"learn":[0.337962584],"iteration":389,"passed_time":0.4101269729,"remaining_time":0.64148065},
{"learn":[0.3377005944],"iteration":390,"passed_time":0.4110424242,"remaining_time":0.6402169728},
{"learn":[0.3374388068],"iteration":391,"passed_time":0.4119170415,"remaining_time":0.6388917378},
{"learn":[0.3371822923],"iteration":392,"passed_time":0.4128130039,"remaining_time":0.6376017643},
{"learn":[0.3369849403],"iteration":393,"passed_time":0.413686756,"remaining_time":0.6362796298},
{"learn":[0.3368308724],"iteration":394,"passed_time":0.4146053948,"remaining_time":0.6350285161},
{"learn":[0.336653346],"iteration":395,"passed_time":0.4155608717,"remaining_time":0.633835269},
{"learn":[0.3363322],"iteration":396,"passed_time":0.4164954044,"remaining_time":0.6326114076},
{"learn":[0.3361420208],"iteration":397,"passed_time":0.4175349942,"remaining_time":0.6315479058},
{"learn":[0.3356765752],"iteration":398,"passed_time":0.4184607578,"remaining_time":0.6303130713},
{"learn":[0.3354643169],"iteration":399,"passed_time":0.4193478107,"remaining_time":0.629021716},
{"learn":[0.3352427656],"iteration":400,"passed_time":0.4203328981,"remaining_time":0.6278788178},
{"learn":[0.3351301415],"iteration":401,"passed_time":0.4212144854,"remaining_time":0.626582742},
{"learn":[0.3348384236],"iteration":402,"passed_time":0.4220947258,"remaining_time":0.6252867278},
{"learn":[0.3347156656],"iteration":403,"passed_time":0.4230800645,"remaining_time":0.6241478179},
{"learn":[0.3343491227],"iteration":404,"passed_time":0.4240116529,"remaining_time":0.6229306999},
{"learn":[0.3342019768],"iteration":405,"passed_time":0.4248931966,"remaining_time":0.6216417705},
{"learn":[0.3340728694],"iteration":406,"passed_time":0.4257967619,"remaining_time":0.6203869282},
{"learn":[0.3338510629],"iteration":407,"passed_time":0.4267191344,"remaining_time":0.619161097},
{"learn":[0.3336875516],"iteration":408,"passed_time":0.4276052407,"remaining_time":0.6178843453},
{"learn":[0.3333405518],"iteration":409,"passed_time":0.4285151725,"remaining_time":0.6166437848},
{"learn":[0.3330705109],"iteration":410,"passed_time":0.4295791852,"remaining_time":0.615625645},
{"learn":[0.3328438172],"iteration":411,"passed_time":0.4304616808,"remaining_time":0.614348224},
{"learn":[0.332559675],"iteration":412,"passed_time":0.4313552621,"remaining_time":0.6130884717},
{"learn":[0.3323860151],"iteration":413,"passed_time":0.4323621982,"remaining_time":0.6119909375},
{"learn":[0.3320747704],"iteration":414,"passed_time":0.433280154,"remaining_time":0.6107684099},
{"learn":[0.3319306154],"iteration":415,"passed_time":0.4342067005,"remaining_time":0.6095594065},
{"learn":[0.3317116939],"iteration":416,"passed_time":0.4351524628,"remaining_time":0.608378623},
{"learn":[0.3314935905],"iteration":417,"passed_time":0.4360670938,"remaining_time":0.6071556187},
{"learn":[0.3312586283],"iteration":418,"passed_time":0.4369281946,"remaining_time":0.6058598593},
{"learn":[0.3310225346],"iteration":419,"passed_time":0.4378866361,"remaining_time":0.6047005927},
{"learn":[0.3306506611],"iteration":420,"passed_time":0.4387643345,"remaining_time":0.6034312343},
{"learn":[0.3304679818],"iteration":421,"passed_time":0.4396394463,"remaining_time":0.6021601895},
{"learn":[0.3301352808],"iteration":422,"passed_time":0.4405346046,"remaining_time":0.6009183614},
{"learn":[0.3299233701],"iteration":423,"passed_time":0.4414365152,"remaining_time":0.5996873414},
{"learn":[0.3296380398],"iteration":424,"passed_time":0.4423321231,"remaining_time":0.598449343},
{"learn":[0.3292718998],"iteration":425,"passed_time":0.4432708382,"remaining_time":0.5972710355},
{"learn":[0.3290441549],"iteration":426,"passed_time":0.4441388522,"remaining_time":0.5959989749},
{"learn":[0.3287277419],"iteration":427,"passed_time":0.445041512,"remaining_time":0.5947751048},
{"learn":[0.3283803309],"iteration":428,"passed_time":0.4460316853,"remaining_time":0.5936692129},
{"learn":[0.3281530863],"iteration":429,"passed_time":0.4469864537,"remaining_time":0.592516927},
{"learn":[0.327793677],"iteration":430,"passed_time":0.4479094576,"remaining_time":0.5913236227},
{"learn":[0.3277258946],"iteration":431,"passed_time":0.4488694591,"remaining_time":0.5901802148},
{"learn":[0.3275651368],"iteration":432,"passed_time":0.4498797622,"remaining_time":0.5891035223},
{"learn":[0.3271954794],"iteration":433,"passed_time":0.450811235,"remaining_time":0.5879243296},
{"learn":[0.3270005024],"iteration":434,"passed_time":0.4517443109,"remaining_time":0.5867483579},
{"learn":[0.3268571712],"iteration":435,"passed_time":0.4526418754,"remaining_time":0.5855275635},
{"learn":[0.326517944],"iteration":436,"passed_time":0.4535778638,"remaining_time":0.5843577513},
{"learn":[0.3263645559],"iteration":437,"passed_time":0.4545268014,"remaining_time":0.5832056218},
{"learn":[0.326180899],"iteration":438,"passed_time":0.4554176882,"remaining_time":0.5819802349},
{"learn":[0.3259272385],"iteration":439,"passed_time":0.4562926912,"remaining_time":0.5807361525},
{"learn":[0.3257885961],"iteration":440,"passed_time":0.4572429237,"remaining_time":0.5795891028},
{"learn":[0.3255575123],"iteration":441,"passed_time":0.4582078236,"remaining_time":0.5784614606},
{"learn":[0.3254104983],"iteration":442,"passed_time":0.4590923098,"remaining_time":0.577233446},
{"learn":[0.3252507625],"iteration":443,"passed_time":0.4601223516,"remaining_time":0.5761892512},
{"learn":[0.3250396605],"iteration":444,"passed_time":0.4610900198,"remaining_time":0.5750673281},
{"learn":[0.3246445231],"iteration":445,"passed_time":0.4620980199,"remaining_time":0.5739961951},
{"learn":[0.3242795378],"iteration":446,"passed_time":0.4630809103,"remaining_time":0.5728942805},
{"learn":[0.3238905857],"iteration":447,"passed_time":0.4641355364,"remaining_time":0.5718812859},
{"learn":[0.323687374],"iteration":448,"passed_time":0.4650336792,"remaining_time":0.570676074},
{"learn":[0.3235293419],"iteration":449,"passed_time":0.4660380245,"remaining_time":0.56960203},
{"learn":[0.3231601938],"iteration":450,"passed_time":0.4670190289,"remaining_time":0.5684998822},
{"learn":[0.3227711624],"iteration":451,"passed_time":0.4680395686,"remaining_time":0.5674462027},
{"learn":[0.3224895012],"iteration":452,"passed_time":0.4690510975,"remaining_time":0.5663817888},
{"learn":[0.3223072143],"iteration":453,"passed_time":0.4700561594,"remaining_time":0.5653098304},
{"learn":[0.3221820657],"iteration":454,"passed_time":0.4709769554,"remaining_time":0.5641372323},
{"learn":[0.3219362576],"iteration":455,"passed_time":0.4719871851,"remaining_time":0.5630724313},
{"learn":[0.3217239095],"iteration":456,"passed_time":0.4728820116,"remaining_time":0.561870749},
{"learn":[0.321513105],"iteration":457,"passed_time":0.4739189406,"remaining_time":0.5608385717},
{"learn":[0.3213586415],"iteration":458,"passed_time":0.4749114345,"remaining_time":0.5597540001},
{"learn":[0.3210463742],"iteration":459,"passed_time":0.475902268,"remaining_time":0.5586678799},
{"learn":[0.3208003396],"iteration":460,"passed_time":0.4768728157,"remaining_time":0.5575584548},
{"learn":[0.3203550014],"iteration":461,"passed_time":0.477861855,"remaining_time":0.5564711645},
{"learn":[0.3199026551],"iteration":462,"passed_time":0.4788362131,"remaining_time":0.5553672709},
{"learn":[0.319666501],"iteration":463,"passed_time":0.4798321567,"remaining_time":0.5542888707},
{"learn":[0.3194614694],"iteration":464,"passed_time":0.4807019706,"remaining_time":0.5530657081},
{"learn":[0.3192069616],"iteration":465,"passed_time":0.4815771814,"remaining_time":0.5518502465},
{"learn":[0.3190371512],"iteration":466,"passed_time":0.4824994868,"remaining_time":0.5506899924},
{"learn":[0.3187662033],"iteration":467,"passed_time":0.4834928093,"remaining_time":0.5496114841},
{"learn":[0.3184387496],"iteration":468,"passed_time":0.4845155176,"remaining_time":0.5485666095},
{"learn":[0.3182736104],"iteration":469,"passed_time":0.4854445966,"remaining_time":0.5474162472},
{"learn":[0.3180801504],"iteration":470,"passed_time":0.4863416097,"remaining_time":0.54623081},
{"learn":[0.3177967883],"iteration":471,"passed_time":0.4872498126,"remaining_time":0.5450591124},
{"learn":[0.3175767962],"iteration":472,"passed_time":0.4881726845,"remaining_time":0.5439048726},
{"learn":[0.3172959575],"iteration":473,"passed_time":0.489074712,"remaining_time":0.5427284779},
{"learn":[0.3171578502],"iteration":474,"passed_time":0.4900118889,"remaining_time":0.5415920877},
{"learn":[0.3168573173],"iteration":475,"passed_time":0.4909475035,"remaining_time":0.5404548147},
{"learn":[0.3163228164],"iteration":476,"passed_time":0.4919259166,"remaining_time":0.5393653132},
{"learn":[0.31623269],"iteration":477,"passed_time":0.4927976743,"remaining_time":0.5381598033},
{"learn":[0.3160878264],"iteration":478,"passed_time":0.4937100436,"remaining_time":0.5369998595},
{"learn":[0.3159678456],"iteration":479,"passed_time":0.494600195,"remaining_time":0.5358168779},
{"learn":[0.3156034838],"iteration":480,"passed_time":0.495495437,"remaining_time":0.5346406067},
{"learn":[0.3153171864],"iteration":481,"passed_time":0.4963804963,"remaining_time":0.5334545583},
{"learn":[0.3150789092],"iteration":482,"passed_time":0.4972503046,"remaining_time":0.5322534316},
{"learn":[0.3147918434],"iteration":483,"passed_time":0.4981805701,"remaining_time":0.5311181285},
{"learn":[0.3146583496],"iteration":484,"passed_time":0.4991006752,"remaining_time":0.5299728819},
{"learn":[0.3144744686],"iteration":485,"passed_time":0.499958976,"remaining_time":0.5287631968},
{"learn":[0.3141961181],"iteration":486,"passed_time":0.5008539951,"remaining_time":0.5275936335},
{"learn":[0.3139924324],"iteration":487,"passed_time":0.5017164869,"remaining_time":0.5263910682},
{"learn":[0.3138089077],"iteration":488,"passed_time":0.5026190809,"remaining_time":0.5252318003},
{"learn":[0.3135970269],"iteration":489,"passed_time":0.5035425775,"remaining_time":0.5240953358},
{"learn":[0.3134697545],"iteration":490,"passed_time":0.5043958487,"remaining_time":0.5228869389},
{"learn":[0.313144885],"iteration":491,"passed_time":0.5053824024,"remaining_time":0.5218176025},
{"learn":[0.3130063587],"iteration":492,"passed_time":0.5062856851,"remaining_time":0.5206629662},
{"learn":[0.3126319246],"iteration":493,"passed_time":0.5072665494,"remaining_time":0.5195888137},
{"learn":[0.3124527687],"iteration":494,"passed_time":0.508192516,"remaining_time":0.5184590315},
{"learn":[0.3120624564],"iteration":495,"passed_time":0.5091255526,"remaining_time":0.5173372551},
{"learn":[0.3118382287],"iteration":496,"passed_time":0.5100531465,"remaining_time":0.5162107297},
{"learn":[0.3116669044],"iteration":497,"passed_time":0.5109825005,"remaining_time":0.5150867776},
{"learn":[0.3114031168],"iteration":498,"passed_time":0.5118951314,"remaining_time":0.5139468153},
{"learn":[0.3112361368],"iteration":499,"passed_time":0.5128054741,"remaining_time":0.5128054741},
{"learn":[0.3110688674],"iteration":500,"passed_time":0.5136689895,"remaining_time":0.5116184147},
{"learn":[0.3109812522],"iteration":501,"passed_time":0.5145650858,"remaining_time":0.5104649656},
{"learn":[0.3107320182],"iteration":502,"passed_time":0.5154796014,"remaining_time":0.5093307394},
{"learn":[0.3105188103],"iteration":503,"passed_time":0.5164016607,"remaining_time":0.5082048089},
{"learn":[0.3103712955],"iteration":504,"passed_time":0.517360504,"remaining_time":0.5071157416},
{"learn":[0.3101948606],"iteration":505,"passed_time":0.5182859288,"remaining_time":0.5059945629},
{"learn":[0.3099363547],"iteration":506,"passed_time":0.5192015372,"remaining_time":0.5048646111},
{"learn":[0.3097099018],"iteration":507,"passed_time":0.5202613614,"remaining_time":0.5038751767},
{"learn":[0.3095639309],"iteration":508,"passed_time":0.5212966694,"remaining_time":0.5028618167},
{"learn":[0.3093266305],"iteration":509,"passed_time":0.5221878341,"remaining_time":0.5017098798},
{"learn":[0.3091160253],"iteration":510,"passed_time":0.5231096439,"remaining_time":0.5005882894},
{"learn":[0.3088714539],"iteration":511,"passed_time":0.5240500865,"remaining_time":0.4994852387},
{"learn":[0.3087262592],"iteration":512,"passed_time":0.5249533621,"remaining_time":0.4983475386},
{"learn":[0.3085244119],"iteration":513,"passed_time":0.5258738263,"remaining_time":0.4972270031},
{"learn":[0.3083794985],"iteration":514,"passed_time":0.5268846874,"remaining_time":0.4961923755},
{"learn":[0.308082816],"iteration":515,"passed_time":0.5278028255,"remaining_time":0.4950708673},
{"learn":[0.3079793249],"iteration":516,"passed_time":0.5287406844,"remaining_time":0.4939685697},
{"learn":[0.3078330313],"iteration":517,"passed_time":0.5296454768,"remaining_time":0.4928361386},
{"learn":[0.3077369666],"iteration":518,"passed_time":0.5306141829,"remaining_time":0.4917638189},
{"learn":[0.3074866618],"iteration":519,"passed_time":0.531516138,"remaining_time":0.4906302813},
{"learn":[0.3073534841],"iteration":520,"passed_time":0.5324198911,"remaining_time":0.4894992857},
{"learn":[0.3070661126],"iteration":521,"passed_time":0.5333957779,"remaining_time":0.4884352143},
{"learn":[0.3069374122],"iteration":522,"passed_time":0.5343865859,"remaining_time":0.4873850889},
{"learn":[0.3067928728],"iteration":523,"passed_time":0.5354365255,"remaining_time":0.4863889049},
{"learn":[0.3065391208],"iteration":524,"passed_time":0.5365287048,"remaining_time":0.4854307329},
{"learn":[0.306199778],"iteration":525,"passed_time":0.537536977,"remaining_time":0.4843964393},
{"learn":[0.3059443764],"iteration":526,"passed_time":0.538465825,"remaining_time":0.4832909587},
{"learn":[0.3057952823],"iteration":527,"passed_time":0.5394747664,"remaining_time":0.4822577457},
{"learn":[0.3055289291],"iteration":528,"passed_time":0.5405839645,"remaining_time":0.481313889},
{"learn":[0.3053686866],"iteration":529,"passed_time":0.5416527398,"remaining_time":0.4803335617},
{"learn":[0.3051157828],"iteration":530,"passed_time":0.5426523533,"remaining_time":0.4792918149},
{"learn":[0.3048605941],"iteration":531,"passed_time":0.5436077204,"remaining_time":0.4782113029},
{"learn":[0.3047087861],"iteration":532,"passed_time":0.5444769801,"remaining_time":0.4770558156},
{"learn":[0.3045913995],"iteration":533,"passed_time":0.5453938223,"remaining_time":0.4759429236},
{"learn":[0.3044570433],"iteration":534,"passed_time":0.5462847821,"remaining_time":0.4748082685},
{"learn":[0.3041561667],"iteration":535,"passed_time":0.5471918113,"remaining_time":0.4736884336},
{"learn":[0.3039030121],"iteration":536,"passed_time":0.5480809957,"remaining_time":0.4725540056},
{"learn":[0.3036434487],"iteration":537,"passed_time":0.548969299,"remaining_time":0.4714197326},
{"learn":[0.3033925628],"iteration":538,"passed_time":0.5498795479,"remaining_time":0.4703051421},
{"learn":[0.3031630033],"iteration":539,"passed_time":0.5509187752,"remaining_time":0.4693011789},
{"learn":[0.3030223482],"iteration":540,"passed_time":0.5521550136,"remaining_time":0.4684642352},
{"learn":[0.3027753093],"iteration":541,"passed_time":0.553142998,"remaining_time":0.4674160389},
{"learn":[0.3025851616],"iteration":542,"passed_time":0.5541139531,"remaining_time":0.4663537322},
{"learn":[0.3023229602],"iteration":543,"passed_time":0.5550007603,"remaining_time":0.4652212255},
{"learn":[0.3020913989],"iteration":544,"passed_time":0.5559457506,"remaining_time":0.4641381955},
{"learn":[0.3019336907],"iteration":545,"passed_time":0.5568753133,"remaining_time":0.4630428429},
{"learn":[0.3018083775],"iteration":546,"passed_time":0.5577581156,"remaining_time":0.4619093718},
{"learn":[0.3015064894],"iteration":547,"passed_time":0.5586329695,"remaining_time":0.4607702595},
{"learn":[0.3014451665],"iteration":548,"passed_time":0.559499725,"remaining_time":0.4596254572},
{"learn":[0.3011294246],"iteration":549,"passed_time":0.560426121,"remaining_time":0.4585304626},
{"learn":[0.3009338409],"iteration":550,"passed_time":0.5613529273,"remaining_time":0.4574364144},
{"learn":[0.3007785094],"iteration":551,"passed_time":0.5622864902,"remaining_time":0.4563484558},
{"learn":[0.3005022441],"iteration":552,"passed_time":0.5631919121,"remaining_time":0.4552383087},
{"learn":[0.3003570685],"iteration":553,"passed_time":0.5641045937,"remaining_time":0.4541347451},
{"learn":[0.3002248518],"iteration":554,"passed_time":0.5651315611,"remaining_time":0.4531235039},
{"learn":[0.2999050395],"iteration":555,"passed_time":0.5660768444,"remaining_time":0.4520469764},
{"learn":[0.2995856433],"iteration":556,"passed_time":0.5670071894,"remaining_time":0.4509590393},
{"learn":[0.2993824213],"iteration":557,"passed_time":0.5679407263,"remaining_time":0.4498741954},
{"learn":[0.2991194162],"iteration":558,"passed_time":0.5688461586,"remaining_time":0.4487677208},
{"learn":[0.2988696558],"iteration":559,"passed_time":0.5697208606,"remaining_time":0.447637819},
{"learn":[0.2987213958],"iteration":560,"passed_time":0.5706234863,"remaining_time":0.4465306782},
{"learn":[0.2985338457],"iteration":561,"passed_time":0.5715043036,"remaining_time":0.4454072687},
{"learn":[0.2983622315],"iteration":562,"passed_time":0.5724010985,"remaining_time":0.4442971226},
{"learn":[0.2981857989],"iteration":563,"passed_time":0.5732740976,"remaining_time":0.4431693379},
{"learn":[0.2980326828],"iteration":564,"passed_time":0.574122875,"remaining_time":0.4420238064},
{"learn":[0.29784618],"iteration":565,"passed_time":0.5750626488,"remaining_time":0.4409490982},
{"learn":[0.2977753459],"iteration":566,"passed_time":0.5759160232,"remaining_time":0.4398088855},
{"learn":[0.2974692572],"iteration":567,"passed_time":0.5768246478,"remaining_time":0.438711704},
{"learn":[0.2972206876],"iteration":568,"passed_time":0.5776772219,"remaining_time":0.4375727287},
{"learn":[0.2970849923],"iteration":569,"passed_time":0.5785972162,"remaining_time":0.4364856193},
{"learn":[0.2968360953],"iteration":570,"passed_time":0.5795069881,"remaining_time":0.4353914149},
{"learn":[0.2966885631],"iteration":571,"passed_time":0.580452952,"remaining_time":0.4343249361},
{"learn":[0.2965203201],"iteration":572,"passed_time":0.5813562957,"remaining_time":0.4332271174},
{"learn":[0.2962944132],"iteration":573,"passed_time":0.5823345626,"remaining_time":0.4321855813},
{"learn":[0.2961358175],"iteration":574,"passed_time":0.5832353052,"remaining_time":0.4310869647},
{"learn":[0.2960316299],"iteration":575,"passed_time":0.5841726676,"remaining_time":0.4300159914},
{"learn":[0.2958211608],"iteration":576,"passed_time":0.5851664999,"remaining_time":0.4289868794},
{"learn":[0.2955444276],"iteration":577,"passed_time":0.5861538818,"remaining_time":0.4279531801},
{"learn":[0.2954825883],"iteration":578,"passed_time":0.5870863447,"remaining_time":0.4268797083},
{"learn":[0.2952987604],"iteration":579,"passed_time":0.587998137,"remaining_time":0.4257917544},
{"learn":[0.2951740075],"iteration":580,"passed_time":0.5888736313,"remaining_time":0.4246782298},
{"learn":[0.2950633782],"iteration":581,"passed_time":0.5897717258,"remaining_time":0.423581755},
{"learn":[0.2947613376],"iteration":582,"passed_time":0.5906792051,"remaining_time":0.4224926733},
{"learn":[0.2946015666],"iteration":583,"passed_time":0.5915922625,"remaining_time":0.421408187},
{"learn":[0.2944148666],"iteration":584,"passed_time":0.5925124707,"remaining_time":0.4203293596},
{"learn":[0.2942003991],"iteration":585,"passed_time":0.5934523113,"remaining_time":0.4192649435},
{"learn":[0.2940013864],"iteration":586,"passed_time":0.5943458471,"remaining_time":0.4181683729},
{"learn":[0.2937854488],"iteration":587,"passed_time":0.5953728438,"remaining_time":0.4171660062},
{"learn":[0.2935650465],"iteration":588,"passed_time":0.596485645,"remaining_time":0.4162234297},
{"learn":[0.2934365773],"iteration":589,"passed_time":0.5975510378,"remaining_time":0.4152473314},
{"learn":[0.293204093],"iteration":590,"passed_time":0.598515819,"remaining_time":0.4142013028},
{"learn":[0.2930501265],"iteration":591,"passed_time":0.5995280242,"remaining_time":0.4131882329},
{"learn":[0.2928151898],"iteration":592,"passed_time":0.600540297,"remaining_time":0.4121752123},
{"learn":[0.2926550799],"iteration":593,"passed_time":0.601475815,"remaining_time":0.4111097322},
{"learn":[0.2924379135],"iteration":594,"passed_time":0.602432717,"remaining_time":0.4100592443},
{"learn":[0.2921590543],"iteration":595,"passed_time":0.6034315595,"remaining_time":0.4090375},
{"learn":[0.2920387997],"iteration":596,"passed_time":0.6043872176,"remaining_time":0.4079866812},
{"learn":[0.2918237316],"iteration":597,"passed_time":0.6053254707,"remaining_time":0.4069244803},
{"learn":[0.2917088301],"iteration":598,"passed_time":0.6062079606,"remaining_time":0.4058253626},
{"learn":[0.2914497356],"iteration":599,"passed_time":0.6070888858,"remaining_time":0.4047259239},
{"learn":[0.2912830345],"iteration":600,"passed_time":0.6080116493,"remaining_time":0.4036549885},
{"learn":[0.291218745],"iteration":601,"passed_time":0.6089017903,"remaining_time":0.4025629777},
{"learn":[0.2910801373],"iteration":602,"passed_time":0.6098245699,"remaining_time":0.4014931248},
{"learn":[0.2910253552],"iteration":603,"passed_time":0.6107357611,"remaining_time":0.4004161613},
{"learn":[0.2906085089],"iteration":604,"passed_time":0.6116923166,"remaining_time":0.3993693638},
{"learn":[0.2902586188],"iteration":605,"passed_time":0.6125952183,"remaining_time":0.3982879802},
{"learn":[0.2901387186],"iteration":606,"passed_time":0.6135363703,"remaining_time":0.3972319498},
{"learn":[0.2897778806],"iteration":607,"passed_time":0.6144503151,"remaining_time":0.3961587558},
{"learn":[0.289596005],"iteration":608,"passed_time":0.6154031686,"remaining_time":0.3951110655},
{"learn":[0.2892791102],"iteration":609,"passed_time":0.6163282464,"remaining_time":0.3940459281},
{"learn":[0.2890777016],"iteration":610,"passed_time":0.6172711591,"remaining_time":0.3929926037},
{"learn":[0.2889255129],"iteration":611,"passed_time":0.6182071267,"remaining_time":0.3919352372},
{"learn":[0.2887606354],"iteration":612,"passed_time":0.6192051424,"remaining_time":0.390917439},
{"learn":[0.2886058319],"iteration":613,"passed_time":0.6201068831,"remaining_time":0.3898391806},
{"learn":[0.2883122391],"iteration":614,"passed_time":0.6210934239,"remaining_time":0.3888145825},
{"learn":[0.287995731],"iteration":615,"passed_time":0.621968337,"remaining_time":0.3877205218},
{"learn":[0.2879389801],"iteration":616,"passed_time":0.6229538461,"remaining_time":0.3866958234},
{"learn":[0.2877030619],"iteration":617,"passed_time":0.6238468349,"remaining_time":0.385614063},
{"learn":[0.2875506042],"iteration":618,"passed_time":0.6247216523,"remaining_time":0.3845217279},
{"learn":[0.2872995627],"iteration":619,"passed_time":0.6256164249,"remaining_time":0.3834423249},
{"learn":[0.2871527709],"iteration":620,"passed_time":0.6264934337,"remaining_time":0.3823526753},
{"learn":[0.2869398989],"iteration":621,"passed_time":0.6274250608,"remaining_time":0.3812969019},
{"learn":[0.2867315789],"iteration":622,"passed_time":0.6283042458,"remaining_time":0.3802097924},
{"learn":[0.2865166883],"iteration":623,"passed_time":0.6291767593,"remaining_time":0.3791193293},
{"learn":[0.2862992198],"iteration":624,"passed_time":0.6300609483,"remaining_time":0.378036569},
{"learn":[0.2860527606],"iteration":625,"passed_time":0.6309514494,"remaining_time":0.3769582142},
{"learn":[0.2859437167],"iteration":626,"passed_time":0.6318850057,"remaining_time":0.375906072},
{"learn":[0.2858197191],"iteration":627,"passed_time":0.6327929663,"remaining_time":0.3748391456},
{"learn":[0.285623544],"iteration":628,"passed_time":0.6337676571,"remaining_time":0.3738120839},
{"learn":[0.2855326633],"iteration":629,"passed_time":0.6346680769,"remaining_time":0.3727415689},
{"learn":[0.285256771],"iteration":630,"passed_time":0.6355599803,"remaining_time":0.3716666129},
{"learn":[0.285142546],"iteration":631,"passed_time":0.6364884412,"remaining_time":0.3706135227},
{"learn":[0.2850440262],"iteration":632,"passed_time":0.637391199,"remaining_time":0.3695459242},
{"learn":[0.2848535851],"iteration":633,"passed_time":0.6384383671,"remaining_time":0.3685622119},
{"learn":[0.2846069668],"iteration":634,"passed_time":0.6393569009,"remaining_time":0.3675043603},
{"learn":[0.2845018505],"iteration":635,"passed_time":0.6402736163,"remaining_time":0.3664459062},
{"learn":[0.2842223362],"iteration":636,"passed_time":0.6411704741,"remaining_time":0.365376581},
{"learn":[0.2841451065],"iteration":637,"passed_time":0.6420716634,"remaining_time":0.3643102542},
{"learn":[0.2837146405],"iteration":638,"passed_time":0.6429917742,"remaining_time":0.3632551338},
{"learn":[0.2836278941],"iteration":639,"passed_time":0.6438652892,"remaining_time":0.3621742252},
{"learn":[0.2834907624],"iteration":640,"passed_time":0.6447858689,"remaining_time":0.3611203229},
{"learn":[0.2832775352],"iteration":641,"passed_time":0.6457068292,"remaining_time":0.3600670481},
{"learn":[0.283249082],"iteration":642,"passed_time":0.6465926865,"remaining_time":0.3589946953},
{"learn":[0.2829317911],"iteration":643,"passed_time":0.6474963085,"remaining_time":0.357932742},
{"learn":[0.2827637962],"iteration":644,"passed_time":0.6483708368,"remaining_time":0.3568552668},
{"learn":[0.2824658244],"iteration":645,"passed_time":0.6493039705,"remaining_time":0.3558105349},
{"learn":[0.282328245],"iteration":646,"passed_time":0.6502405344,"remaining_time":0.3547680196},
{"learn":[0.2820492829],"iteration":647,"passed_time":0.6511860194,"remaining_time":0.3537306772},
{"learn":[0.2817914819],"iteration":648,"passed_time":0.6521309335,"remaining_time":0.3526933092},
{"learn":[0.2816593111],"iteration":649,"passed_time":0.653050481,"remaining_time":0.3516425667},
{"learn":[0.2814508593],"iteration":650,"passed_time":0.653949055,"remaining_time":0.3505809834},
{"learn":[0.281374091],"iteration":651,"passed_time":0.6548099759,"remaining_time":0.3494998031},
{"learn":[0.2812767605],"iteration":652,"passed_time":0.6556887666,"remaining_time":0.3484287933},
{"learn":[0.2811000329],"iteration":653,"passed_time":0.6566828843,"remaining_time":0.3474193853},
{"learn":[0.280986448],"iteration":654,"passed_time":0.6576809667,"remaining_time":0.3464121122},
{"learn":[0.2807589834],"iteration":655,"passed_time":0.6585707404,"remaining_time":0.3453480712},
{"learn":[0.2805419348],"iteration":656,"passed_time":0.6595100627,"remaining_time":0.3443104284},
{"learn":[0.2804035466],"iteration":657,"passed_time":0.6604515053,"remaining_time":0.3432741866},
{"learn":[0.2801920941],"iteration":658,"passed_time":0.6613320026,"remaining_time":0.3422066963},
{"learn":[0.2799328496],"iteration":659,"passed_time":0.662249302,"remaining_time":0.3411587314},
{"learn":[0.2795634284],"iteration":660,"passed_time":0.6631682059,"remaining_time":0.3401119846},
{"learn":[0.2794585526],"iteration":661,"passed_time":0.6640835351,"remaining_time":0.3390637989},
{"learn":[0.2792721146],"iteration":662,"passed_time":0.6649574164,"remaining_time":0.3379949462},
{"learn":[0.2789887762],"iteration":663,"passed_time":0.6658386809,"remaining_time":0.3369304169},
{"learn":[0.2787634577],"iteration":664,"passed_time":0.6667468261,"remaining_time":0.3358799801},
{"learn":[0.2785318962],"iteration":665,"passed_time":0.6676694051,"remaining_time":0.3348372091},
{"learn":[0.2783006809],"iteration":666,"passed_time":0.6686055791,"remaining_time":0.3338015859},
{"learn":[0.2777463387],"iteration":667,"passed_time":0.6695020365,"remaining_time":0.3327465211},
{"learn":[0.2776117516],"iteration":668,"passed_time":0.670407553,"remaining_time":0.3316964126},
{"learn":[0.2774214796],"iteration":669,"passed_time":0.6713038571,"remaining_time":0.3306421983},
{"learn":[0.2772449313],"iteration":670,"passed_time":0.6722118263,"remaining_time":0.3295941741},
{"learn":[0.2769815761],"iteration":671,"passed_time":0.6731005176,"remaining_time":0.3285371574},
{"learn":[0.2767594562],"iteration":672,"passed_time":0.6739871714,"remaining_time":0.3274796509},
{"learn":[0.2765736206],"iteration":673,"passed_time":0.6748807522,"remaining_time":0.3264260018},
{"learn":[0.2765051142],"iteration":674,"passed_time":0.6757496399,"remaining_time":0.3253609377},
{"learn":[0.2763350606],"iteration":675,"passed_time":0.6766997768,"remaining_time":0.324335396},
{"learn":[0.2760790012],"iteration":676,"passed_time":0.6775882769,"remaining_time":0.3232806698},
{"learn":[0.2759739045],"iteration":677,"passed_time":0.6784799844,"remaining_time":0.3222279572},
{"learn":[0.2757759244],"iteration":678,"passed_time":0.6793769289,"remaining_time":0.3211781947},
{"learn":[0.2754570719],"iteration":679,"passed_time":0.6802788087,"remaining_time":0.3201312041},
{"learn":[0.2752632375],"iteration":680,"passed_time":0.6811740096,"remaining_time":0.3190815111},
{"learn":[0.2751624693],"iteration":681,"passed_time":0.6820844516,"remaining_time":0.3180393777},
{"learn":[0.2749570952],"iteration":682,"passed_time":0.6829772122,"remaining_time":0.3169894235},
{"learn":[0.2748463841],"iteration":683,"passed_time":0.684123379,"remaining_time":0.3160569996},
{"learn":[0.2746929985],"iteration":684,"passed_time":0.68513208,"remaining_time":0.3150607375},
{"learn":[0.2744594415],"iteration":685,"passed_time":0.6861103251,"remaining_time":0.3140504987},
{"learn":[0.2740444129],"iteration":686,"passed_time":0.6870060395,"remaining_time":0.3130027516},
{"learn":[0.273837238],"iteration":687,"passed_time":0.6880451239,"remaining_time":0.3120204631},
{"learn":[0.273512674],"iteration":688,"passed_time":0.6889441924,"remaining_time":0.3109748096},
{"learn":[0.2733439251],"iteration":689,"passed_time":0.6898216574,"remaining_time":0.3099198751},
{"learn":[0.2730063891],"iteration":690,"passed_time":0.6906831032,"remaining_time":0.3088582907},
{"learn":[0.2727891856],"iteration":691,"passed_time":0.6916092251,"remaining_time":0.3078260713},
{"learn":[0.2725039613],"iteration":692,"passed_time":0.6925320606,"remaining_time":0.3067927022},
{"learn":[0.2723578336],"iteration":693,"passed_time":0.6934284641,"remaining_time":0.3057479971},
{"learn":[0.2722036641],"iteration":694,"passed_time":0.6942971047,"remaining_time":0.3046915352},
{"learn":[0.2720817186],"iteration":695,"passed_time":0.6952268283,"remaining_time":0.3036622928},
{"learn":[0.2719332534],"iteration":696,"passed_time":0.6961482676,"remaining_time":0.3026297347},
{"learn":[0.2717478623],"iteration":697,"passed_time":0.6970457137,"remaining_time":0.301587114},
{"learn":[0.2716178441],"iteration":698,"passed_time":0.6979432578,"remaining_time":0.3005449508},
{"learn":[0.2714999175],"iteration":699,"passed_time":0.6989942344,"remaining_time":0.2995689576},
{"learn":[0.2713489787],"iteration":700,"passed_time":0.6999366094,"remaining_time":0.2985464282},
{"learn":[0.271186549],"iteration":701,"passed_time":0.7008830191,"remaining_time":0.29752584},
{"learn":[0.270951908],"iteration":702,"passed_time":0.7018004226,"remaining_time":0.2964932084},
{"learn":[0.2708086445],"iteration":703,"passed_time":0.7026886624,"remaining_time":0.2954486422},
{"learn":[0.2705884993],"iteration":704,"passed_time":0.7035805134,"remaining_time":0.2944060304},
{"learn":[0.2704099608],"iteration":705,"passed_time":0.7044714803,"remaining_time":0.2933634776},
{"learn":[0.2702608321],"iteration":706,"passed_time":0.7053889198,"remaining_time":0.2923323246},
{"learn":[0.2701687832],"iteration":707,"passed_time":0.7062707215,"remaining_time":0.2912867948},
{"learn":[0.2698740608],"iteration":708,"passed_time":0.7071712128,"remaining_time":0.2902493976},
{"learn":[0.269677001],"iteration":709,"passed_time":0.7080621962,"remaining_time":0.2892085027},
{"learn":[0.2695620949],"iteration":710,"passed_time":0.7090509497,"remaining_time":0.28820777},
{"learn":[0.2694981933],"iteration":711,"passed_time":0.7099589699,"remaining_time":0.2871744148},
{"learn":[0.2691658885],"iteration":712,"passed_time":0.7108739289,"remaining_time":0.2861442042},
{"learn":[0.2690333141],"iteration":713,"passed_time":0.7117280559,"remaining_time":0.2850899496},
{"learn":[0.2689234066],"iteration":714,"passed_time":0.7125906693,"remaining_time":0.2840396374},
{"learn":[0.2686320038],"iteration":715,"passed_time":0.7134934185,"remaining_time":0.2830057694},
{"learn":[0.2684390091],"iteration":716,"passed_time":0.7145266389,"remaining_time":0.282023764},
{"learn":[0.2681757273],"iteration":717,"passed_time":0.7154543094,"remaining_time":0.2810001605},
{"learn":[0.2679893394],"iteration":718,"passed_time":0.7164603775,"remaining_time":0.2800074633},
{"learn":[0.2678466522],"iteration":719,"passed_time":0.7173924817,"remaining_time":0.2789859651},
{"learn":[0.267446642],"iteration":720,"passed_time":0.7183510885,"remaining_time":0.2779749704},
{"learn":[0.2671399904],"iteration":721,"passed_time":0.7194151073,"remaining_time":0.2770047089},
{"learn":[0.2668948963],"iteration":722,"passed_time":0.7203941287,"remaining_time":0.2760016233},
{"learn":[0.2666525386],"iteration":723,"passed_time":0.7212976716,"remaining_time":0.2749698306},
{"learn":[0.2664858378],"iteration":724,"passed_time":0.7223213743,"remaining_time":0.2739839696},
{"learn":[0.2663036513],"iteration":725,"passed_time":0.7232766254,"remaining_time":0.2729721699},
{"learn":[0.2662432057],"iteration":726,"passed_time":0.7241695313,"remaining_time":0.2719371142},
{"learn":[0.2660618841],"iteration":727,"passed_time":0.7251207562,"remaining_time":0.2709242386},
{"learn":[0.2659603578],"iteration":728,"passed_time":0.7260010893,"remaining_time":0.2698851786},
{"learn":[0.2658521752],"iteration":729,"passed_time":0.7268901882,"remaining_time":0.2688497956},
{"learn":[0.265516045],"iteration":730,"passed_time":0.7277686736,"remaining_time":0.2678109072},
{"learn":[0.2650685777],"iteration":731,"passed_time":0.728779945,"remaining_time":0.2668210727},
{"learn":[0.2649892971],"iteration":732,"passed_time":0.7296968592,"remaining_time":0.2657968095},
{"learn":[0.2646218384],"iteration":733,"passed_time":0.7306063622,"remaining_time":0.2647701531},
{"learn":[0.2644244428],"iteration":734,"passed_time":0.7315489326,"remaining_time":0.2637557376},
{"learn":[0.2643086442],"iteration":735,"passed_time":0.7324973533,"remaining_time":0.2627436159},
{"learn":[0.2641801965],"iteration":736,"passed_time":0.7333528599,"remaining_time":0.2616985104},
{"learn":[0.2640556243],"iteration":737,"passed_time":0.7342645745,"remaining_time":0.2606738733},
{"learn":[0.263831089],"iteration":738,"passed_time":0.7351449645,"remaining_time":0.2596384787},
{"learn":[0.263598425],"iteration":739,"passed_time":0.736022979,"remaining_time":0.2586026683},
{"learn":[0.2633922195],"iteration":740,"passed_time":0.7369405879,"remaining_time":0.2575811232},
{"learn":[0.2632304145],"iteration":741,"passed_time":0.7378293976,"remaining_time":0.2565498444},
{"learn":[0.2631092746],"iteration":742,"passed_time":0.7387412311,"remaining_time":0.255526913},
{"learn":[0.262898487],"iteration":743,"passed_time":0.7396963336,"remaining_time":0.2545191685},
{"learn":[0.2627485466],"iteration":744,"passed_time":0.7406139004,"remaining_time":0.2534987176},
{"learn":[0.2625802809],"iteration":745,"passed_time":0.7416342286,"remaining_time":0.2525135309},
{"learn":[0.2623413637],"iteration":746,"passed_time":0.742522024,"remaining_time":0.2514833629},
{"learn":[0.26212636],"iteration":747,"passed_time":0.7434308403,"remaining_time":0.2504606574},
{"learn":[0.2620168902],"iteration":748,"passed_time":0.7443342744,"remaining_time":0.2494364524},
{"learn":[0.2619226203],"iteration":749,"passed_time":0.7452277279,"remaining_time":0.2484092426},
{"learn":[0.2617129094],"iteration":750,"passed_time":0.7461106958,"remaining_time":0.2473789124},
{"learn":[0.2615073157],"iteration":751,"passed_time":0.7469968886,"remaining_time":0.2463500377},
{"learn":[0.2613259292],"iteration":752,"passed_time":0.7480349048,"remaining_time":0.2453713433},
{"learn":[0.2612015993],"iteration":753,"passed_time":0.748949498,"remaining_time":0.2443522235},
{"learn":[0.2610318278],"iteration":754,"passed_time":0.7498847515,"remaining_time":0.2433400849},
{"learn":[0.2607883694],"iteration":755,"passed_time":0.7507924466,"remaining_time":0.2423192552},
{"learn":[0.2606022268],"iteration":756,"passed_time":0.7517207839,"remaining_time":0.2413053507},
{"learn":[0.2605527862],"iteration":757,"passed_time":0.752586316,"remaining_time":0.2402716207},
{"learn":[0.2603407504],"iteration":758,"passed_time":0.75352033,"remaining_time":0.2392600784},
{"learn":[0.2602330124],"iteration":759,"passed_time":0.7544289399,"remaining_time":0.2382407179},
{"learn":[0.2601051401],"iteration":760,"passed_time":0.755308494,"remaining_time":0.2372125231},
{"learn":[0.2599530897],"iteration":761,"passed_time":0.7561878683,"remaining_time":0.2361846623},
{"learn":[0.2597662612],"iteration":762,"passed_time":0.7571748237,"remaining_time":0.2351906071},
{"learn":[0.2596392064],"iteration":763,"passed_time":0.7581057765,"remaining_time":0.2341792713},
{"learn":[0.2592611809],"iteration":764,"passed_time":0.7591021877,"remaining_time":0.2331882537},
{"learn":[0.2591696009],"iteration":765,"passed_time":0.760031607,"remaining_time":0.2321767572},
{"learn":[0.2589851295],"iteration":766,"passed_time":0.7609505397,"remaining_time":0.2311622891},
{"learn":[0.2587952823],"iteration":767,"passed_time":0.7620573491,"remaining_time":0.2302048242},
{"learn":[0.258718658],"iteration":768,"passed_time":0.763020435,"remaining_time":0.2292037978},
{"learn":[0.258545005],"iteration":769,"passed_time":0.7640217788,"remaining_time":0.2282142976},
{"learn":[0.258383062],"iteration":770,"passed_time":0.7649702387,"remaining_time":0.2272090592},
{"learn":[0.2579916381],"iteration":771,"passed_time":0.7660209162,"remaining_time":0.2262341566},
{"learn":[0.2578259839],"iteration":772,"passed_time":0.7671279386,"remaining_time":0.2252756042},
{"learn":[0.2577324015],"iteration":773,"passed_time":0.7682231417,"remaining_time":0.2243132171},
{"learn":[0.2575833791],"iteration":774,"passed_time":0.7692290223,"remaining_time":0.2233245549},
{"learn":[0.2573086235],"iteration":775,"passed_time":0.7702730407,"remaining_time":0.2223468571},
{"learn":[0.2570540561],"iteration":776,"passed_time":0.7712795759,"remaining_time":0.2213582309},
{"learn":[0.2567969356],"iteration":777,"passed_time":0.7723921556,"remaining_time":0.2203998182},
{"learn":[0.2566622289],"iteration":778,"passed_time":0.7734021581,"remaining_time":0.2194119088},
{"learn":[0.2565303836],"iteration":779,"passed_time":0.7744252838,"remaining_time":0.2184276442},
{"learn":[0.2563045556],"iteration":780,"passed_time":0.7755078147,"remaining_time":0.2174599378},
{"learn":[0.2560972418],"iteration":781,"passed_time":0.7767227501,"remaining_time":0.2165288485},
{"learn":[0.2559034353],"iteration":782,"passed_time":0.7776875483,"remaining_time":0.2155277113},
{"learn":[0.2557740851],"iteration":783,"passed_time":0.7787281273,"remaining_time":0.2145475453},
{"learn":[0.2557041187],"iteration":784,"passed_time":0.7797158841,"remaining_time":0.2135527581},
{"learn":[0.2554376858],"iteration":785,"passed_time":0.7806575851,"remaining_time":0.2125454494},
{"learn":[0.2553647839],"iteration":786,"passed_time":0.7815430552,"remaining_time":0.2115230886},
{"learn":[0.2552865252],"iteration":787,"passed_time":0.7825059835,"remaining_time":0.2105219143},
{"learn":[0.2552316682],"iteration":788,"passed_time":0.7834369424,"remaining_time":0.2095122875},
{"learn":[0.2550972439],"iteration":789,"passed_time":0.7845361736,"remaining_time":0.2085475904},
{"learn":[0.2548664024],"iteration":790,"passed_time":0.7855465372,"remaining_time":0.2075590724},
{"learn":[0.2547089771],"iteration":791,"passed_time":0.7866922822,"remaining_time":0.2066060539},
{"learn":[0.2546334051],"iteration":792,"passed_time":0.7877463186,"remaining_time":0.2056286103},
{"learn":[0.2544511106],"iteration":793,"passed_time":0.7887616701,"remaining_time":0.2046409371},
{"learn":[0.2542704977],"iteration":794,"passed_time":0.7898202249,"remaining_time":0.2036643347},
{"learn":[0.2537648951],"iteration":795,"passed_time":0.790976014,"remaining_time":0.2027124458},
{"learn":[0.2536250114],"iteration":796,"passed_time":0.7918709674,"remaining_time":0.201693609},
{"learn":[0.253461784],"iteration":797,"passed_time":0.7928730774,"remaining_time":0.2007022076},
{"learn":[0.2532739738],"iteration":798,"passed_time":0.7938391364,"remaining_time":0.1997017102},
{"learn":[0.2531221307],"iteration":799,"passed_time":0.7947181027,"remaining_time":0.1986795257},
{"learn":[0.2530333164],"iteration":800,"passed_time":0.7955860983,"remaining_time":0.1976549732},
{"learn":[0.2528168297],"iteration":801,"passed_time":0.7966139545,"remaining_time":0.196670278},
{"learn":[0.252676654],"iteration":802,"passed_time":0.7977222429,"remaining_time":0.1957052078},
{"learn":[0.2524935207],"iteration":803,"passed_time":0.7987238195,"remaining_time":0.1947137669},
{"learn":[0.2523333958],"iteration":804,"passed_time":0.7997492416,"remaining_time":0.1937280772},
{"learn":[0.2520498073],"iteration":805,"passed_time":0.8007042854,"remaining_time":0.1927253491},
{"learn":[0.2517285537],"iteration":806,"passed_time":0.8018082461,"remaining_time":0.1917583538},
{"learn":[0.251614643],"iteration":807,"passed_time":0.8028687372,"remaining_time":0.19078069},
{"learn":[0.2514852233],"iteration":808,"passed_time":0.8038084731,"remaining_time":0.1897743119},
{"learn":[0.2513789934],"iteration":809,"passed_time":0.8047650366,"remaining_time":0.1887720456},
{"learn":[0.2510734915],"iteration":810,"passed_time":0.8057790493,"remaining_time":0.1877832803},
{"learn":[0.250780476],"iteration":811,"passed_time":0.8067279442,"remaining_time":0.1867793762},
{"learn":[0.2505103319],"iteration":812,"passed_time":0.8076652669,"remaining_time":0.1857729458},
{"learn":[0.2504052189],"iteration":813,"passed_time":0.8087101073,"remaining_time":0.184791253},
{"learn":[0.2502708523],"iteration":814,"passed_time":0.8098541225,"remaining_time":0.1838319174},
{"learn":[0.2502005116],"iteration":815,"passed_time":0.8108023605,"remaining_time":0.1828279833},
{"learn":[0.2499479019],"iteration":816,"passed_time":0.8118247654,"remaining_time":0.1818407981},
{"learn":[0.2497824452],"iteration":817,"passed_time":0.8128374283,"remaining_time":0.1808513593},
{"learn":[0.2496525048],"iteration":818,"passed_time":0.8137444508,"remaining_time":0.1798385172},
{"learn":[0.2495222503],"iteration":819,"passed_time":0.8146463505,"remaining_time":0.1788248087},
{"learn":[0.2494290952],"iteration":820,"passed_time":0.815620135,"remaining_time":0.1778270453},
{"learn":[0.2493213028],"iteration":821,"passed_time":0.8165376465,"remaining_time":0.1768171546},
{"learn":[0.2491801974],"iteration":822,"passed_time":0.8175230079,"remaining_time":0.1758220807},
{"learn":[0.2491407712],"iteration":823,"passed_time":0.8185023175,"remaining_time":0.1748257377},
{"learn":[0.2490106634],"iteration":824,"passed_time":0.8195667751,"remaining_time":0.1738474977},
{"learn":[0.2487798837],"iteration":825,"passed_time":0.8204750381,"remaining_time":0.172836146},
{"learn":[0.2486918277],"iteration":826,"passed_time":0.8213640087,"remaining_time":0.1718210079},
{"learn":[0.2485173579],"iteration":827,"passed_time":0.8223506679,"remaining_time":0.1708264672},
{"learn":[0.2483464527],"iteration":828,"passed_time":0.823397976,"remaining_time":0.1698444558},
{"learn":[0.2482338952],"iteration":829,"passed_time":0.8243713156,"remaining_time":0.1688471369},
{"learn":[0.2481620113],"iteration":830,"passed_time":0.8253105058,"remaining_time":0.1678429308},
{"learn":[0.2480589711],"iteration":831,"passed_time":0.8262499147,"remaining_time":0.1668389251},
{"learn":[0.2479041454],"iteration":832,"passed_time":0.8271659136,"remaining_time":0.1658303812},
{"learn":[0.2477729479],"iteration":833,"passed_time":0.8280434221,"remaining_time":0.1648143982},
{"learn":[0.2476752306],"iteration":834,"passed_time":0.828934726,"remaining_time":0.1638014728},
{"learn":[0.2474200787],"iteration":835,"passed_time":0.8299003084,"remaining_time":0.1628034098},
{"learn":[0.2472923369],"iteration":836,"passed_time":0.8307624405,"remaining_time":0.1617852781},
{"learn":[0.2471504111],"iteration":837,"passed_time":0.8316992714,"remaining_time":0.1607819594},
{"learn":[0.2469023848],"iteration":838,"passed_time":0.8327064545,"remaining_time":0.1597922994},
{"learn":[0.2467406882],"iteration":839,"passed_time":0.8337908033,"remaining_time":0.1588172959},
{"learn":[0.2465987366],"iteration":840,"passed_time":0.8347934638,"remaining_time":0.1578265883},
{"learn":[0.2464713253],"iteration":841,"passed_time":0.8358466903,"remaining_time":0.1568453409},
{"learn":[0.2462152982],"iteration":842,"passed_time":0.8368735148,"remaining_time":0.1558590057},
{"learn":[0.2459306516],"iteration":843,"passed_time":0.8378840194,"remaining_time":0.1548695581},
{"learn":[0.2457626097],"iteration":844,"passed_time":0.8388637772,"remaining_time":0.1538744207},
{"learn":[0.2454721293],"iteration":845,"passed_time":0.8398797885,"remaining_time":0.1528859189},
{"learn":[0.2453180267],"iteration":846,"passed_time":0.8407652284,"remaining_time":0.1518737662},
{"learn":[0.2451679285],"iteration":847,"passed_time":0.8417185007,"remaining_time":0.1508740709},
{"learn":[0.2450456077],"iteration":848,"passed_time":0.8426852545,"remaining_time":0.1498768827},
{"learn":[0.2447461137],"iteration":849,"passed_time":0.8436837434,"remaining_time":0.1488853665},
{"learn":[0.2446537573],"iteration":850,"passed_time":0.8445858031,"remaining_time":0.1478769503},
{"learn":[0.2445050563],"iteration":851,"passed_time":0.8455171335,"remaining_time":0.1468738683},
{"learn":[0.244399551],"iteration":852,"passed_time":0.8464224613,"remaining_time":0.1458664734},
{"learn":[0.2439759906],"iteration":853,"passed_time":0.8474352145,"remaining_time":0.144877683},
{"learn":[0.2438403585],"iteration":854,"passed_time":0.8483357611,"remaining_time":0.1438698074},
{"learn":[0.2435885271],"iteration":855,"passed_time":0.8492726838,"remaining_time":0.142868302},
{"learn":[0.2434062137],"iteration":856,"passed_time":0.8501595137,"remaining_time":0.1418585886},
{"learn":[0.2432576995],"iteration":857,"passed_time":0.8510461889,"remaining_time":0.1408491362},
{"learn":[0.2432099879],"iteration":858,"passed_time":0.851940438,"remaining_time":0.1398412128},
{"learn":[0.2431470467],"iteration":859,"passed_time":0.8528092977,"remaining_time":0.1388294206},
{"learn":[0.2429615067],"iteration":860,"passed_time":0.8537791284,"remaining_time":0.1378342611},
{"learn":[0.2427843112],"iteration":861,"passed_time":0.8547227997,"remaining_time":0.1368349726},
{"learn":[0.2427455857],"iteration":862,"passed_time":0.8555999187,"remaining_time":0.1358252478},
{"learn":[0.2425870963],"iteration":863,"passed_time":0.85651103,"remaining_time":0.1348211806},
{"learn":[0.2425034589],"iteration":864,"passed_time":0.8574181477,"remaining_time":0.1338167051},
{"learn":[0.2423668538],"iteration":865,"passed_time":0.8583067893,"remaining_time":0.1328095956},
{"learn":[0.2421905645],"iteration":866,"passed_time":0.8591786076,"remaining_time":0.1318001786},
{"learn":[0.2420616617],"iteration":867,"passed_time":0.860180851,"remaining_time":0.1308109128},
{"learn":[0.2418491618],"iteration":868,"passed_time":0.8611412988,"remaining_time":0.1298153166},
{"learn":[0.2418142621],"iteration":869,"passed_time":0.8620546975,"remaining_time":0.1288127709},
{"learn":[0.2415990769],"iteration":870,"passed_time":0.8629924754,"remaining_time":0.1278140406},
{"learn":[0.2414797087],"iteration":871,"passed_time":0.8638690232,"remaining_time":0.1268064621},
{"learn":[0.2412574305],"iteration":872,"passed_time":0.8647677638,"remaining_time":0.1258024124},
{"learn":[0.241100055],"iteration":873,"passed_time":0.8656791599,"remaining_time":0.1248004281},
{"learn":[0.2409149565],"iteration":874,"passed_time":0.8666201368,"remaining_time":0.1238028767},
{"learn":[0.2407085865],"iteration":875,"passed_time":0.8675244456,"remaining_time":0.122800264},
{"learn":[0.240592283],"iteration":876,"passed_time":0.8684399683,"remaining_time":0.1217994482},
{"learn":[0.2404796675],"iteration":877,"passed_time":0.869384651,"remaining_time":0.1208028786},
{"learn":[0.2403224047],"iteration":878,"passed_time":0.8702561498,"remaining_time":0.1197963528},
{"learn":[0.2401482082],"iteration":879,"passed_time":0.8711827304,"remaining_time":0.118797645},
{"learn":[0.2398619944],"iteration":880,"passed_time":0.8721108008,"remaining_time":0.1177993023},
{"learn":[0.2396510525],"iteration":881,"passed_time":0.87306481,"remaining_time":0.1168045891},
{"learn":[0.2395183212],"iteration":882,"passed_time":0.8740641863,"remaining_time":0.1158159794},
{"learn":[0.2394081867],"iteration":883,"passed_time":0.8749783668,"remaining_time":0.1148161658},
{"learn":[0.2391359524],"iteration":884,"passed_time":0.8758853951,"remaining_time":0.1138156163},
{"learn":[0.2389793826],"iteration":885,"passed_time":0.876870802,"remaining_time":0.1128253628},
{"learn":[0.2388684199],"iteration":886,"passed_time":0.8778023179,"remaining_time":0.1118282547},
{"learn":[0.2385695019],"iteration":887,"passed_time":0.8787420955,"remaining_time":0.1108323364},
{"learn":[0.2383091117],"iteration":888,"passed_time":0.8796435792,"remaining_time":0.109831763},
{"learn":[0.2382755048],"iteration":889,"passed_time":0.8805257643,"remaining_time":0.108829027},
{"learn":[0.2380859562],"iteration":890,"passed_time":0.8814661789,"remaining_time":0.1078336852},
{"learn":[0.2378720532],"iteration":891,"passed_time":0.8823770076,"remaining_time":0.1068348843},
{"learn":[0.2377231223],"iteration":892,"passed_time":0.883331174,"remaining_time":0.1058414733},
{"learn":[0.2374846049],"iteration":893,"passed_time":0.8842498899,"remaining_time":0.1048439467},
{"learn":[0.2373962554],"iteration":894,"passed_time":0.885184008,"remaining_time":0.1038484032},
{"learn":[0.2372393557],"iteration":895,"passed_time":0.886075034,"remaining_time":0.102847995},
{"learn":[0.2371898119],"iteration":896,"passed_time":0.8870186419,"remaining_time":0.1018538686},
{"learn":[0.2368465572],"iteration":897,"passed_time":0.8879985265,"remaining_time":0.1008639752},
{"learn":[0.2367044009],"iteration":898,"passed_time":0.8889287807,"remaining_time":0.0998685282},
{"learn":[0.2364881633],"iteration":899,"passed_time":0.8898129895,"remaining_time":0.09886810995},
{"learn":[0.2362324257],"iteration":900,"passed_time":0.8907244969,"remaining_time":0.09787094916},
{"learn":[0.2359124075],"iteration":901,"passed_time":0.8915896764,"remaining_time":0.09686894489},
{"learn":[0.2358249883],"iteration":902,"passed_time":0.8926027524,"remaining_time":0.09588313066},
{"learn":[0.2353734502],"iteration":903,"passed_time":0.89364845,"remaining_time":0.09490072036},
{"learn":[0.2352477373],"iteration":904,"passed_time":0.8946439932,"remaining_time":0.09391290537},
{"learn":[0.2350487442],"iteration":905,"passed_time":0.8955381969,"remaining_time":0.09291455906},
{"learn":[0.2349198878],"iteration":906,"passed_time":0.8964260074,"remaining_time":0.09191578687},
{"learn":[0.2347490288],"iteration":907,"passed_time":0.8973427564,"remaining_time":0.09092019118},
{"learn":[0.2345476269],"iteration":908,"passed_time":0.8982510772,"remaining_time":0.08992392522},
{"learn":[0.2343596749],"iteration":909,"passed_time":0.8991249344,"remaining_time":0.08892444406},
{"learn":[0.2341856485],"iteration":910,"passed_time":0.9000390832,"remaining_time":0.08792917497},
{"learn":[0.2340546164],"iteration":911,"passed_time":0.9009310463,"remaining_time":0.08693194306},
{"learn":[0.2340207484],"iteration":912,"passed_time":0.9018302327,"remaining_time":0.08593563006},
{"learn":[0.2338615669],"iteration":913,"passed_time":0.9027108569,"remaining_time":0.08493778303},
{"learn":[0.2336780473],"iteration":914,"passed_time":0.9036059082,"remaining_time":0.08394153246},
{"learn":[0.2334101546],"iteration":915,"passed_time":0.9045300788,"remaining_time":0.08294817316},
{"learn":[0.233238525],"iteration":916,"passed_time":0.9054345924,"remaining_time":0.08195318558},
{"learn":[0.2331125562],"iteration":917,"passed_time":0.9063939815,"remaining_time":0.08096329682},
{"learn":[0.2329170534],"iteration":918,"passed_time":0.9073501882,"remaining_time":0.07997319395},
{"learn":[0.2327629156],"iteration":919,"passed_time":0.9082577219,"remaining_time":0.07897893234},
{"learn":[0.2326573903],"iteration":920,"passed_time":0.9091796519,"remaining_time":0.07798609392},
{"learn":[0.2324365431],"iteration":921,"passed_time":0.9100975042,"remaining_time":0.07699306434},
{"learn":[0.2322426375],"iteration":922,"passed_time":0.9110021144,"remaining_time":0.07599909297},
{"learn":[0.2319812777],"iteration":923,"passed_time":0.9119114049,"remaining_time":0.07500569997},
{"learn":[0.2317837623],"iteration":924,"passed_time":0.912820287,"remaining_time":0.0740124557},
{"learn":[0.2315948705],"iteration":925,"passed_time":0.9137087417,"remaining_time":0.07301776121},
{"learn":[0.2315366745],"iteration":926,"passed_time":0.914591251,"remaining_time":0.07202282775},
{"learn":[0.2314990574],"iteration":927,"passed_time":0.9154458351,"remaining_time":0.07102596996},
{"learn":[0.2313681856],"iteration":928,"passed_time":0.916369495,"remaining_time":0.07003469768},
{"learn":[0.2311460476],"iteration":929,"passed_time":0.9172325987,"remaining_time":0.0690390128},
{"learn":[0.2309287446],"iteration":930,"passed_time":0.9180999785,"remaining_time":0.06804392966},
{"learn":[0.2308417465],"iteration":931,"passed_time":0.9190260649,"remaining_time":0.06705340388},
{"learn":[0.2307275566],"iteration":932,"passed_time":0.9199291114,"remaining_time":0.0660613617},
{"learn":[0.2306351608],"iteration":933,"passed_time":0.920837524,"remaining_time":0.06506988928},
{"learn":[0.2303814544],"iteration":934,"passed_time":0.9217921613,"remaining_time":0.064081808},
{"learn":[0.2302198054],"iteration":935,"passed_time":0.9227508295,"remaining_time":0.06309407381},
{"learn":[0.2301131858],"iteration":936,"passed_time":0.9236916933,"remaining_time":0.06210520457},
{"learn":[0.2299363265],"iteration":937,"passed_time":0.9246170016,"remaining_time":0.06111540949},
{"learn":[0.2298140963],"iteration":938,"passed_time":0.9255288337,"remaining_time":0.06012487631},
{"learn":[0.229711791],"iteration":939,"passed_time":0.9264162647,"remaining_time":0.05913295306},
{"learn":[0.2295699455],"iteration":940,"passed_time":0.9274145543,"remaining_time":0.05814820266},
{"learn":[0.2294900938],"iteration":941,"passed_time":0.9282950351,"remaining_time":0.05715616989},
{"learn":[0.2293715076],"iteration":942,"passed_time":0.9292096899,"remaining_time":0.05616643937},
{"learn":[0.2292764727],"iteration":943,"passed_time":0.9301138164,"remaining_time":0.05517624335},
{"learn":[0.2292522435],"iteration":944,"passed_time":0.9309945177,"remaining_time":0.05418486611},
{"learn":[0.2291335662],"iteration":945,"passed_time":0.9318995932,"remaining_time":0.0531951142},
{"learn":[0.2290044527],"iteration":946,"passed_time":0.9327583285,"remaining_time":0.05220294763},
{"learn":[0.2289090429],"iteration":947,"passed_time":0.9336402055,"remaining_time":0.05121233195},
{"learn":[0.2287793174],"iteration":948,"passed_time":0.9345441361,"remaining_time":0.0502231306},
{"learn":[0.2285819784],"iteration":949,"passed_time":0.9354381646,"remaining_time":0.04923358761},
{"learn":[0.2284439272],"iteration":950,"passed_time":0.9364626283,"remaining_time":0.04825096613},
{"learn":[0.228399326],"iteration":951,"passed_time":0.9374549853,"remaining_time":0.04726663792},
{"learn":[0.2282466756],"iteration":952,"passed_time":0.938364292,"remaining_time":0.04627819698},
{"learn":[0.2281549852],"iteration":953,"passed_time":0.9392704456,"remaining_time":0.04528976991},
{"learn":[0.2280420758],"iteration":954,"passed_time":0.9401590583,"remaining_time":0.04430068861},
{"learn":[0.2278957318],"iteration":955,"passed_time":0.941085034,"remaining_time":0.04331353713},
{"learn":[0.227746179],"iteration":956,"passed_time":0.9420887806,"remaining_time":0.04233000791},
{"learn":[0.2276104138],"iteration":957,"passed_time":0.9429837132,"remaining_time":0.04134166592},
{"learn":[0.2274142991],"iteration":958,"passed_time":0.9438950842,"remaining_time":0.04035422154},
{"learn":[0.2272558716],"iteration":959,"passed_time":0.9448789406,"remaining_time":0.03936995586},
{"learn":[0.227199839],"iteration":960,"passed_time":0.9458294168,"remaining_time":0.03838433637},
{"learn":[0.2270902606],"iteration":961,"passed_time":0.9467698769,"remaining_time":0.0373983943},
{"learn":[0.2268615988],"iteration":962,"passed_time":0.9476654999,"remaining_time":0.03641082398},
{"learn":[0.226759571],"iteration":963,"passed_time":0.9486421439,"remaining_time":0.03542647011},
{"learn":[0.2266351706],"iteration":964,"passed_time":0.9495469643,"remaining_time":0.0344395272},
{"learn":[0.2265667491],"iteration":965,"passed_time":0.950466757,"remaining_time":0.0334532813},
{"learn":[0.2263211084],"iteration":966,"passed_time":0.95135641,"remaining_time":0.03246614429},
{"learn":[0.2261860757],"iteration":967,"passed_time":0.9522918632,"remaining_time":0.03148072275},
{"learn":[0.2260427932],"iteration":968,"passed_time":0.953220291,"remaining_time":0.03049517959},
{"learn":[0.2258781815],"iteration":969,"passed_time":0.9541166552,"remaining_time":0.02950876253},
{"learn":[0.2257335853],"iteration":970,"passed_time":0.9550421794,"remaining_time":0.02852340186},
{"learn":[0.2255368573],"iteration":971,"passed_time":0.9559281536,"remaining_time":0.027537025},
{"learn":[0.2254414863],"iteration":972,"passed_time":0.9568553621,"remaining_time":0.02655199874},
{"learn":[0.2252900075],"iteration":973,"passed_time":0.9577607145,"remaining_time":0.02556650778},
{"learn":[0.2251867006],"iteration":974,"passed_time":0.9586380924,"remaining_time":0.02458046391},
{"learn":[0.2249910163],"iteration":975,"passed_time":0.9595116278,"remaining_time":0.02359454822},
{"learn":[0.2249162925],"iteration":976,"passed_time":0.960458081,"remaining_time":0.02261057918},
{"learn":[0.2246737191],"iteration":977,"passed_time":0.9613576006,"remaining_time":0.0216256311},
{"learn":[0.2246410039],"iteration":978,"passed_time":0.9622627158,"remaining_time":0.02064097756},
{"learn":[0.2244622022],"iteration":979,"passed_time":0.9631705188,"remaining_time":0.0196565412},
{"learn":[0.22433378],"iteration":980,"passed_time":0.9640250163,"remaining_time":0.01867122865},
{"learn":[0.2242285423],"iteration":981,"passed_time":0.9649574258,"remaining_time":0.01768761066},
{"learn":[0.2241733125],"iteration":982,"passed_time":0.9658562241,"remaining_time":0.01670351557},
{"learn":[0.223962913],"iteration":983,"passed_time":0.9667325092,"remaining_time":0.01571922779},
{"learn":[0.2237643163],"iteration":984,"passed_time":0.9677306186,"remaining_time":0.0147370145},
{"learn":[0.2236266056],"iteration":985,"passed_time":0.9686446126,"remaining_time":0.01375357462},
{"learn":[0.223514932],"iteration":986,"passed_time":0.9695333498,"remaining_time":0.0127699428},
{"learn":[0.2234594847],"iteration":987,"passed_time":0.9704682147,"remaining_time":0.01178706334},
{"learn":[0.2232926064],"iteration":988,"passed_time":0.9714515638,"remaining_time":0.01080482022},
{"learn":[0.2231921464],"iteration":989,"passed_time":0.9723829628,"remaining_time":0.00982205013},
{"learn":[0.223105328],"iteration":990,"passed_time":0.9733570123,"remaining_time":0.00883977105},
{"learn":[0.2229251692],"iteration":991,"passed_time":0.9742496773,"remaining_time":0.007856852237},
{"learn":[0.2227482657],"iteration":992,"passed_time":0.9751802122,"remaining_time":0.00687438216},
{"learn":[0.2224572426],"iteration":993,"passed_time":0.9761092438,"remaining_time":0.005892007508},
{"learn":[0.2223390648],"iteration":994,"passed_time":0.9770372239,"remaining_time":0.004909734793},
{"learn":[0.2222072557],"iteration":995,"passed_time":0.9779159384,"remaining_time":0.003927373246},
{"learn":[0.2221542115],"iteration":996,"passed_time":0.9787855828,"remaining_time":0.002945192326},
{"learn":[0.221921571],"iteration":997,"passed_time":0.9796899588,"remaining_time":0.001963306531},
{"learn":[0.2218483751],"iteration":998,"passed_time":0.980558413,"remaining_time":0.0009815399529},
{"learn":[0.2216472087],"iteration":999,"passed_time":0.9815691983,"remaining_time":0}
]}